Workbook

Sheet Notes & Sources
A1: Usio, Inc. (NASDAQ: USIO) — Quarterly Integrated 3-Statement Model
A2: Notes, Sources, Street Reconciliation & Guidance Tie-Out
A4: Structure
A5: Quarterly columns run 2025Q1 through 2028Q4 with annual subtotal columns (FY2025A, FY2026E, FY2027E, FY2028E) shaded dark blue. 2025Q1-Q4 and 2026Q1 are ACTUAL (light green fill, black font for reported figures). 2026Q2-2028Q4 are projected. All KPI/driver inputs are on the Assumptions tab in BLUE.
A7: Guidance & Street reconciliation (see 'Guidance & Street Recon' tab)
A8: - Management guidance (8-K, 3/18/2026): FY2026 revenue growth of 10-12%, continued positive Adjusted EBITDA. Midpoint = 11.0% growth -> FY2026E revenue = FY2025A revenue ($85.39M) x 1.11 = $94.78M. The model's quarterly build (2026Q1A actual $25.47M + Q2-Q4 estimates) is calibrated so FY2026E ties to this midpoint.
A9: - Street consensus (Seeking Alpha, pulled 3/31/2026): FY2026 consensus revenue $93.89M, consensus EPS $(0.04). 2026Q1 actual revenue of $25.47M beat consensus by 9% and Adj. EBITDA of $0.8M beat consensus by 12% (per company 8-K 5/13/2026 press release headline).
A10: - The 'Guidance & Street Recon' tab shows the model's FY2026E vs. (a) guidance midpoint and (b) Street consensus, with variances explained.
A12: Primary sources
A13: - 10-Q filings for Q1 2025 (filed ~5/2025), Q2 2025 (~8/2025), Q3 2025 (~11/2025), and Q1 2026 (filed ~5/13/2026): exact quarterly revenue, cost of services, gross profit, SBC, SG&A, D&A, operating income, interest income/expense, other income, tax, net income, diluted shares, and FULL balance sheets for 12/31/2025 and 3/31/2026.
A14: - 8-K earnings releases for Q4/FY2025 (3/18/2026) and Q1 2026 (5/13/2026): revenue growth rates, Adjusted EBITDA, operating cash flow, cash balances, share repurchases, segment revenue detail (ACH, Credit Card, Prepaid, Output Solutions), and FY2026 guidance (10-12% revenue growth, positive Adj. EBITDA).
A15: - FY2025 10-K (filed 3/18/2026): full-year SG&A $18.4M (+10% YoY), capitalized software $1,102,368, PostCredit acquisition (Nov 2025), gross margin 23.1% (2025) vs 23.7% (2024).
... A37: - PROJECTIONS (2026Q2-2028): each of the four revenue segments and all three interest lines grows at the same consolidated YoY growth rate (Assumptions row 8), which is itself calibrated so FY2026E ties to the 11% guidance midpoint. This means segment MIX is held roughly constant going forward (Prepaid drifts down slightly as a % of revenue due to 2026Q1's lower base). If more granular segment guidance becomes available (e.g., from the school-voucher and PostCredit program ramps discussed on the Q1 2026 earnings call, which should disproportionately benefit ACH and Credit Card), segment growth rates should be de-linked and set independently.

Sheet Assumptions
A1: Usio, Inc. — Assumptions & KPI Drivers (Quarterly)
A2: BLUE = hardcoded KPI/driver inputs (editable). GREEN = FY2026E reconciled to guidance midpoint (10-12% growth -> 11.0%).
A3: Light green columns = reported ACTUAL quarters. All $ in thousands.
A5: Driver / Period | B5: 2025Q1A | C5: 2025Q2A | D5: 2025Q3A | E5: 2025Q4A | F5: FY2025A | G5: 2026Q1A | H5: 2026Q2E | I5: 2026Q3E | J5: 2026Q4E | K5: FY2026E | L5: 2027Q1E | M5: 2027Q2E | N5: 2027Q3E | O5: 2027Q4E | P5: FY2027E | Q5: 2028Q1E | R5: 2028Q2E | S5: 2028Q3E | T5: 2028Q4E | U5: FY2028E
A7: REVENUE & GROWTH DRIVERS
A8: Revenue YoY growth % (quarterly) | G8: 0.1576 | H8: 0.10769442 | I8: 0.10769442 | J8: 0.067694423 | L8: 0.08 | M8: 0.08 | N8: 0.08 | O8: 0.08 | Q8: 0.08 | R8: 0.08 | S8: 0.08 | T8: 0.08 | W8: Q2-Q4 2026 growth rates (10.77% / 10.77% / 6.77%) are CALIBRATED so that FY2026E revenue = FY2025A revenue x 1.11 exactly, i.e. the midpoint of management's 10-12% guidance (8-K 3/18/2026). Q4'26 is set ~4pp lower than Q2/Q3 because Q4'25 already grew +8% YoY (a tougher base comparison). 2027-28: 8%/qtr assumption reflecting continued 'Usio One' cross-sell momentum per management commentary, moderating from the 2026 guidance range.
A9: Gross margin % (quarterly) | H9: 0.225 | I9: 0.228 | J9: 0.23 | L9: 0.225 | M9: 0.225 | N9: 0.225 | O9: 0.225 | Q9: 0.225 | R9: 0.225 | S9: 0.225 | T9: 0.225 | W9: 2025 actuals computed directly from reported GP/Revenue (21.9% / 25.8% / 23.0% / 21.9% by quarter; Q2'25 8-K notes gross margins improved 185bps to 25.8%). 2026Q1 actual was 20.2% (10-Q), management commentary (5/13/2026 8-K) says 'margins are expected to improve over the balance of the year' — Q2-Q4'26 assumptions step up modestly from 22.5% to 23.0%. 2027-28 held at 22.5%, slightly below FY2025's 23.1% reflecting continued mix shift toward lower-margin ACH/complementary revenue per 10-K commentary.
A10: Stock-based compensation (% of revenue) | H10: 0.013 | I10: 0.013 | J10: 0.013 | L10: 0.013 | M10: 0.013 | N10: 0.013 | O10: 0.013 | Q10: 0.013 | R10: 0.013 | S10: 0.013 | T10: 0.013 | W10: 2026Q1 actual SBC was $329,284 / $25,465,774 = 1.29%. 2025 quarterly SBC ranged 1.6%-2.2% of revenue (10-Qs); the downward trend (2026Q1 lower than all 2025 quarters) reflects management's 5/13/2026 commentary that Total SG&A was 'down...primarily due to lower...stock-based compensation expense'. 1.3% held for 2026Q2-2028.
A11: Other SG&A (% of revenue) | H11: 0.165 | I11: 0.165 | J11: 0.165 | L11: 0.165 | M11: 0.165 | N11: 0.165 | O11: 0.165 | Q11: 0.165 | R11: 0.165 | S11: 0.165 | T11: 0.165 | W11: 2026Q1 actual other SG&A was $4,356,142 / $25,465,774 = 17.1%. Management's 8-K 5/13/2026 states SG&A 'is now at a level that is not expected to materially increase this year' after a sequential $700K reduction. As revenue grows through 2026-28 with SG&A roughly flat in dollar terms, this ratio is assumed to decline modestly to 16.5% (operating leverage).
A12: Depreciation & amortization (% of revenue) | H12: 0.011 | I12: 0.011 | J12: 0.011 | L12: 0.011 | M12: 0.011 | N12: 0.011 | O12: 0.011 | Q12: 0.011 | R12: 0.011 | S12: 0.011 | T12: 0.011 | W12: 2026Q1 actual D&A was $225,745 / $25,465,774 = 0.89%, sharply down from ~2.0-2.5% in 2025 quarters because intangibles were nearly fully amortized by 12/31/2025 ($9,759 net per 10-K). 1.1% assumed forward, allowing for amortization of newly capitalized software/PP&E from ongoing capex.
A13: Effective tax rate % | H13: 0.3 | I13: 0.3 | J13: 0.3 | L13: 0.3 | M13: 0.3 | N13: 0.3 | O13: 0.3 | Q13: 0.3 | R13: 0.3 | S13: 0.3 | T13: 0.3 | W13: 2026Q1 actual effective tax rate was $171,874 / $294,377 pretax = 58.4% (federal $67,084 + state $104,790), reflecting state tax burden on modest pretax income plus continued conservatism on DTA utilization. 30% assumed for 2026Q2-2028 as pretax income normalizes (blended state + reduced federal burden as NOLs are utilized).
A14: Other income, net ($000/quarter) | H14: 137 | I14: 137 | J14: 137 | L14: 137 | M14: 137 | N14: 137 | O14: 137 | Q14: 137 | R14: 137 | S14: 137 | T14: 137 | W14: 2026Q1 actual 'other income, net' = interest income $91.5K - interest expense $22.8K + other income $68.7K = $137.3K. Held flat at $137K/quarter for 2026Q2-2028 (no specific guidance on interest income trajectory; settlement balances roughly stable as % of revenue).
A15: Diluted weighted avg. shares (000) | H15: 27800 | I15: 27800 | J15: 27800 | L15: 27800 | M15: 27800 | N15: 27800 | O15: 27800 | Q15: 27800 | R15: 27800 | S15: 27800 | T15: 27800 | W15: 2026Q1 actual diluted weighted avg shares = 27,748,037 (10-Q). Modest continued dilution from option exercises offsetting buybacks assumed (27,800K held through 2028).
A17: WORKING CAPITAL & BALANCE SHEET DRIVERS
A18: Days Sales Outstanding (AR) - days | H18: 19 | I18: 19 | J18: 19 | L18: 19 | M18: 19 | N18: 19 | O18: 19 | Q18: 19 | R18: 19 | S18: 19 | T18: 19 | W18: AR was $5,274,586 at 12/31/2025 and $5,418,653 at 3/31/2026 (10-Q actuals). On a quarterly revenue base of ~$22-25M, this implies ~19-20 days. Held at 19 days for 2026Q2-2028.
A19: Days Payable Outstanding (AP) - days | H19: 7 | I19: 7 | J19: 7 | L19: 7 | M19: 7 | N19: 7 | O19: 7 | Q19: 7 | R19: 7 | S19: 7 | T19: 7 | W19: AP was $880,590 at 12/31/2025 and $1,275,061 at 3/31/2026 (10-Q actuals), vs Q1'26 cost of services of $20.3M / 91 days = $223K/day -> ~5.7 days; rounded to 7 to allow for modest growth.
A20: Settlement processing assets/obligations (% of revenue, quarterly) | H20: 2.8 | I20: 2.8 | J20: 2.8 | L20: 2.8 | M20: 2.8 | N20: 2.8 | O20: 2.8 | Q20: 2.8 | R20: 2.8 | S20: 2.8 | T20: 2.8 | W20: Settlement processing assets EXACTLY equal settlement processing obligations at both 12/31/2025 ($74.18M) and 3/31/2026 ($69.52M) per the 10-Q — confirming Usio passes these balances through 1:1 (asset = liability). As a multiple of quarterly revenue: $74.18M/$22.24M=3.33x (12/31/25) and $69.52M/$25.47M=2.73x (3/31/26). 2.80x assumed forward (mid-range, reflecting quarter-end volume timing volatility).
A21: Prepaid card load assets/obligations (% of revenue, quarterly) | H21: 0.65 | I21: 0.65 | J21: 0.65 | L21: 0.65 | M21: 0.65 | N21: 0.65 | O21: 0.65 | Q21: 0.65 | R21: 0.65 | S21: 0.65 | T21: 0.65 | W21: Prepaid card load assets EXACTLY equal prepaid card load obligations: $27.62M (12/31/25) and $15.47M (3/31/26) — also a 1:1 pass-through. As multiple of quarterly revenue: 1.24x (12/31/25) and 0.61x (3/31/26), a sharp Q4->Q1 decline reflecting seasonal prepaid card loads (holiday gift cards). 0.65x assumed as a non-seasonal baseline for 2026Q2-2028 (mid-year levels typically below Q4 holiday peak).
A22: Customer deposits (% of revenue, quarterly) | H22: 0.1 | I22: 0.1 | J22: 0.1 | L22: 0.1 | M22: 0.1 | N22: 0.1 | O22: 0.1 | Q22: 0.1 | R22: 0.1 | S22: 0.1 | T22: 0.1 | W22: Customer deposits $2.28M (12/31/25) and $2.24M (3/31/26) vs quarterly revenue of $22.24M/$25.47M = 0.10x / 0.09x. Held at 0.10x.
A23: Merchant reserves (% of revenue, quarterly) | H23: 0.2 | I23: 0.2 | J23: 0.2 | L23: 0.2 | M23: 0.2 | N23: 0.2 | O23: 0.2 | Q23: 0.2 | R23: 0.2 | S23: 0.2 | T23: 0.2 | W23: Merchant reserves $4.80M (12/31/25) and $4.62M (3/31/26) vs quarterly revenue = 0.22x / 0.18x. Held at 0.20x.
A24: Capex & capitalized software (% of revenue, quarterly) | H24: 0.02 | I24: 0.02 | J24: 0.02 | L24: 0.02 | M24: 0.02 | N24: 0.02 | O24: 0.02 | Q24: 0.02 | R24: 0.02 | S24: 0.02 | T24: 0.02 | W24: 2026Q1 actual capex + capitalized software = ($398,072 + $215,532) / $25,465,774 = 2.41%, elevated due to the new printer install (10-K: 'new printer in September 2025 that will be installed and operational in the first half of 2026'). 2.0% assumed as a normalized run-rate for 2026Q2-2028.
A25: Share repurchases ($000/quarter) | H25: 150 | I25: 150 | J25: 150 | L25: 150 | M25: 150 | N25: 150 | O25: 150 | Q25: 150 | R25: 150 | S25: 150 | T25: 150 | W25: 2026Q1 actual buybacks = $233,459 (10-Q). FY2025 totaled $1.1M (~$275K/qtr avg). $150K/quarter assumed for 2026Q2-2028, a modest pace consistent with 'strong, essentially unlevered balance sheet' commentary supporting ongoing repurchases (10-K).

Sheet Revenue Build
A1: Usio, Inc. — Revenue Build: Segment Detail & Processing Volume Drivers
A2: ($ in thousands except volume/transaction KPIs). BLUE = hardcoded actuals or KPI drivers.
A4: Fiscal Period | B4: 2025Q1A | C4: 2025Q2A | D4: 2025Q3A | E4: 2025Q4A | F4: FY2025A | G4: 2026Q1A | H4: 2026Q2E | I4: 2026Q3E | J4: 2026Q4E | K4: FY2026E | L4: 2027Q1E | M4: 2027Q2E | N4: 2027Q3E | O4: 2027Q4E | P4: FY2027E | Q4: 2028Q1E | R4: 2028Q2E | S4: 2028Q3E | T4: 2028Q4E | U4: FY2028E
A6: PROCESSING VOLUME & TRANSACTION KPIs (memo)
A7: Total payment dollar volume processed ($B) | B7: 2 | C7: 2.0045 | D7: 2.18 | E7: 2.2155 | F7: =SUM(B7:E7) -> 8.4 | G7: 2.5 | H7: =C7*(1+H9) -> 2.24504 | I7: =D7*(1+I9) -> 2.4416 | J7: =E7*(1+J9) -> 2.48136 | K7: =SUM(G7:J7) -> 9.668 | L7: =G7*(1+L9) -> 2.8 | M7: =H7*(1+M9) -> 2.5144448 | N7: =I7*(1+N9) -> 2.734592 | O7: =J7*(1+O9) -> 2.7791232 | P7: =SUM(L7:O7) -> 10.82816 | Q7: =L7*(1+Q9) -> 3.136 | R7: =M7*(1+R9) -> 2.8161782 | S7: =N7*(1+S9) -> 3.062743 | T7: =O7*(1+T9) -> 3.112618 | U7: =SUM(Q7:T7) -> 12.127539 | W7: ACTUALS: Q1 2025 = $2.0B (8-K 5/14/2025, +34% YoY, implies Q1 2024 ~$1.49B); Q3 2025 = $2.18B (8-K 11/12/2025, +8% YoY); 2026Q1 = $2.50B (10-Q/earnings call, +28% YoY). FY2025 total = $8.4B (+19% YoY from $7.1B in FY2024, per 8-K 3/18/2026 / Annual Letter). Q2 2025 ($2.00B) and Q4 2025 ($2.22B) are ESTIMATED RESIDUALS (FY2025 total minus Q1+Q3, split ~evenly with a slight seasonal Q4 skew) since exact quarterly $ volumes for Q2/Q4 2025 were not located in the retrieved disclosures -- Q2 growth of +15% YoY and Q4 growth were qualitatively disclosed but absolute dollar figures were not. 2026Q2-2028: prior-year-quarter x (1+ volume growth %, row 9 below) -- a memo metric, NOT used directly to drive revenue (revenue is segment-driven below), but shown for cross-checking against management's volume commentary.
A8: Total payment transactions processed (millions) | B8: 13.7 | C8: 14.4875 | D8: 16.2 | E8: 16.0125 | F8: =SUM(B8:E8) -> 60.4 | G8: 16.71 | H8: =C8*(1+H10) -> 16.660625 | I8: =D8*(1+I10) -> 18.63 | J8: =E8*(1+J10) -> 18.414375 | K8: =SUM(G8:J8) -> 70.415 | L8: =G8*(1+L10) -> 19.2165 | M8: =H8*(1+M10) -> 19.159719 | N8: =I8*(1+N10) -> 21.4245 | O8: =J8*(1+O10) -> 21.176531 | P8: =SUM(L8:O8) -> 80.97725 | Q8: =L8*(1+Q10) -> 22.098975 | R8: =M8*(1+R10) -> 22.033677 | S8: =N8*(1+S10) -> 24.638175 | T8: =O8*(1+T10) -> 24.353011 | U8: =SUM(Q8:T8) -> 93.123837 | W8: ACTUALS: Q1 2025 = 13.7M (+41% YoY, 8-K 5/14/2025); Q3 2025 = 16.2M (+27% YoY, 8-K 11/12/2025); 2026Q1 = 16.7M (= 13.7M x 1.22, +22% YoY per earnings call -- 10-Q press release rounds total Q1'26 transactions slightly differently). FY2025 total = 60.4M (+29% YoY from 47.0M in FY2024, per Annual Letter 1/21/2026). Q2 2025 (14.5M) and Q4 2025 (16.0M) are ESTIMATED RESIDUALS (FY2025 total minus Q1+Q3, split with a slight Q4 seasonal skew) -- exact figures not located in retrieved disclosures.
A9: Volume growth % YoY (driver for 2026Q2-2028) | B9: 0.34 | C9: 0.15 | D9: 0.08 | G9: 0.28 | H9: 0.12 | I9: 0.12 | J9: 0.12 | L9: 0.12 | M9: 0.12 | N9: 0.12 | O9: 0.12 | Q9: 0.12 | R9: 0.12 | S9: 0.12 | T9: 0.12 | W9: 2026Q2-2028: 12% YoY volume growth assumed (between the +28% pace of 2026Q1 and the high single digits seen in slower 2025 quarters), reflecting moderation from the record-volume momentum cited in the Q1 2026 earnings call as new programs (school voucher disbursements >$1B, PostCredit) ramp through 2026-2028.
A10: Transaction growth % YoY (driver for 2026Q2-2028) | B10: 0.41 | D10: 0.27 | G10: 0.22 | H10: 0.15 | I10: 0.15 | J10: 0.15 | L10: 0.15 | M10: 0.15 | N10: 0.15 | O10: 0.15 | Q10: 0.15 | R10: 0.15 | S10: 0.15 | T10: 0.15 | W10: 2026Q2-2028: 15% YoY transaction growth assumed, consistent with the company's multi-year trend of transaction growth outpacing dollar volume growth (driven by smaller-ticket, higher-frequency ACH/PINless debit transactions).
A11: Prepaid card load volume ($M, annual only -- memo) | F11: 300 | W11: FY2025 prepaid card load volume fell to ~$300M from ~$500M in FY2024 (Annual Letter 1/21/2026), driven by the loss of a reseller's amusement park card program. Quarterly split not disclosed.
A13: SEGMENT REVENUE ($000)
A14: ACH & Complementary Services | B14: 5044.517 | C14: 5192.224 | D14: 5844.267 | E14: 6085.659 | F14: =SUM(B14:E14) -> 22166.667 | G14: 6305.646 | H14: =C14*(1+Assumptions!H8) -> 5751.3976 | I14: =D14*(1+Assumptions!I8) -> 6473.662 | J14: =E14*(1+Assumptions!J8) -> 6497.6242 | K14: =SUM(G14:J14) -> 25028.33 | L14: =G14*(1+Assumptions!L8) -> 6810.0977 | M14: =H14*(1+Assumptions!M8) -> 6211.5094 | N14: =I14*(1+Assumptions!N8) -> 6991.5549 | O14: =J14*(1+Assumptions!O8) -> 7017.4341 | P14: =SUM(L14:O14) -> 27030.596 | Q14: =L14*(1+Assumptions!Q8) -> 7354.9055 | R14: =M14*(1+Assumptions!R8) -> 6708.4301 | S14: =N14*(1+Assumptions!S8) -> 7550.8793 | T14: =O14*(1+Assumptions!T8) -> 7578.8288 | U14: =SUM(Q14:T14) -> 29193.044 | W14: ACTUALS: Q1 2025 = $5,044.5K (10-Q segment table, exact). Q2 2025 = $5,192.2K and Q3 2025 = $5,844.3K (10-Qs, exact, derived from disclosed cumulative figures). Q4 2025 = $6,085.7K (back-solved: FY2025 ACH grew $5.5M / 33% per 8-K 3/18/2026, so FY2025 ACH = FY2024 ACH x 1.33; Q4 = FY total less 9-month actual). 2026Q1 = $6,305.6K actual (10-Q/earnings call: ACH revenue +25% YoY). 2026Q2-2028: prior-year-quarter x (1 + total revenue growth driver, Assumptions row 8) -- i.e., this segment is assumed to grow in line with the consolidated growth rate used to calibrate to guidance.
A15: Credit Card (incl. PayFac) | B15: 7878.694 | C15: 7045.03 | D15: 7351.4 | E15: 7600 | F15: =SUM(B15:E15) -> 29875.124 | G15: 9690.794 | H15: =C15*(1+Assumptions!H8) -> 7803.7404 | I15: =D15*(1+Assumptions!I8) -> 8143.1048 | J15: =E15*(1+Assumptions!J8) -> 8114.4776 | K15: =SUM(G15:J15) -> 33752.117 | L15: =G15*(1+Assumptions!L8) -> 10466.058 | M15: =H15*(1+Assumptions!M8) -> 8428.0397 | N15: =I15*(1+Assumptions!N8) -> 8794.5532 | O15: =J15*(1+Assumptions!O8) -> 8763.6358 | P15: =SUM(L15:O15) -> 36452.286 | Q15: =L15*(1+Assumptions!Q8) -> 11303.342 | R15: =M15*(1+Assumptions!R8) -> 9102.2829 | S15: =N15*(1+Assumptions!S8) -> 9498.1174 | T15: =O15*(1+Assumptions!T8) -> 9464.7267 | U15: =SUM(Q15:T15) -> 39368.469 | W15: ACTUALS: Q1 2025 = $7,878.7K, Q2 2025 = $7,045.0K, Q3 2025 = $7,351.4K (10-Qs, exact, PayFac was >50% of card revenue by Q1 2025). Q4 2025 = $7,600.0K (estimated; FY2025 credit card revenue grew 3% per 8-K 3/18/2026, with non-legacy PayFac book growing 7% mitigating legacy attrition -- Q4 figure is the implied residual). 2026Q1 = $9,690.8K actual (10-Q/earnings call: 'record $9.7 million', +23% YoY, PayFac = 78% of segment revenue). 2026Q2-2028: prior-year-quarter x (1 + total revenue growth driver, Assumptions row 8).
A16: Output Solutions | B16: 5732.867 | C16: 5297.198 | D16: 5885.582 | E16: 6305.495 | F16: =SUM(B16:E16) -> 23221.142 | G16: 6822.112 | H16: =C16*(1+Assumptions!H8) -> 5867.6767 | I16: =D16*(1+Assumptions!I8) -> 6519.4264 | J16: =E16*(1+Assumptions!J8) -> 6732.3418 | K16: =SUM(G16:J16) -> 25941.557 | L16: =G16*(1+Assumptions!L8) -> 7367.881 | M16: =H16*(1+Assumptions!M8) -> 6337.0908 | N16: =I16*(1+Assumptions!N8) -> 7040.9805 | O16: =J16*(1+Assumptions!O8) -> 7270.9292 | P16: =SUM(L16:O16) -> 28016.881 | Q16: =L16*(1+Assumptions!Q8) -> 7957.3114 | R16: =M16*(1+Assumptions!R8) -> 6844.0581 | S16: =N16*(1+Assumptions!S8) -> 7604.2589 | T16: =O16*(1+Assumptions!T8) -> 7852.6035 | U16: =SUM(Q16:T16) -> 30258.232 | W16: ACTUALS: Q1 2025 = $5,732.9K (10-Q, exact, +4% YoY). Q2/Q3 2025 estimated as residuals (see segment allocation methodology note below); FY2025 Output Solutions revenue was roughly flat YoY per 8-K 3/18/2026 ('Output Solutions revenues were flat on the year... with revenue ramping up especially in the fourth quarter'). 2026Q1 = $6,822.1K actual (10-Q/earnings call: +19% YoY, 'accelerated from 8% in the preceding quarter' -- consistent with Q4 2025 acceleration). 2026Q2-2028: prior-year-quarter x (1 + total revenue growth driver, Assumptions row 8). The new high-speed printer (operational H1 2026, per 10-K) supports continued growth in this segment.
A17: Prepaid Card Services | B17: 2907.451 | C17: 2014.874 | D17: 1641.695 | E17: 1758.824 | F17: =SUM(B17:E17) -> 8322.844 | G17: 2384.11 | H17: =C17*(1+Assumptions!H8) -> 2231.8647 | I17: =D17*(1+Assumptions!I8) -> 1818.4964 | J17: =E17*(1+Assumptions!J8) -> 1877.8866 | K17: =SUM(G17:J17) -> 8312.3577 | L17: =G17*(1+Assumptions!L8) -> 2574.8388 | M17: =H17*(1+Assumptions!M8) -> 2410.4139 | N17: =I17*(1+Assumptions!N8) -> 1963.9761 | O17: =J17*(1+Assumptions!O8) -> 2028.1175 | P17: =SUM(L17:O17) -> 8977.3463 | Q17: =L17*(1+Assumptions!Q8) -> 2780.8259 | R17: =M17*(1+Assumptions!R8) -> 2603.247 | S17: =N17*(1+Assumptions!S8) -> 2121.0942 | T17: =O17*(1+Assumptions!T8) -> 2190.3669 | U17: =SUM(Q17:T17) -> 9695.534 | W17: ACTUALS: Q1 2025 = $2,907.5K (10-Q, exact, -13% YoY as COVID-era prepaid programs wound down). Q2 2025 down ~26% YoY (8-K 8/6/2025, loss of a reseller's downstream customer); Q3 2025 prepaid card LOAD VOLUME down 46% YoY (8-K 11/12/2025). FY2025 prepaid card load volume fell to ~$300M from ~$500M (Annual Letter 1/21/2026), driven by the loss of a reseller's amusement park card program. 2026Q1 = $2,384.1K actual (10-Q/earnings call: -18% YoY, 'weaker prepaid card services'). Quarterly Q2-Q4 2025 dollar splits are ESTIMATED (allocated from the known quarterly total-revenue residual, scaling down the prepaid share progressively per the disclosed volume-decline commentary). 2026Q2-2028: prior-year-quarter x (1 + total revenue growth driver, Assumptions row 8) -- this likely OVERSTATES prepaid given the structural decline, but is retained for simplicity since prepaid is now a small (~10%) and shrinking share of total revenue; consider lowering this segment's growth assumption independently if more granular guidance becomes available.
A18: Interest Revenue, by segment
A19: Interest - ACH & complementary services | B19: 224.129 | C19: 207.096 | D19: 230.099 | E19: 246.516 | F19: =SUM(B19:E19) -> 907.84 | G19: 132.365 | H19: =C19*(1+Assumptions!H8) -> 229.39908 | I19: =D19*(1+Assumptions!I8) -> 254.87938 | J19: =E19*(1+Assumptions!J8) -> 263.20376 | K19: =SUM(G19:J19) -> 879.84722 | L19: =G19*(1+Assumptions!L8) -> 142.9542 | M19: =H19*(1+Assumptions!M8) -> 247.75101 | N19: =I19*(1+Assumptions!N8) -> 275.26973 | O19: =J19*(1+Assumptions!O8) -> 284.26006 | P19: =SUM(L19:O19) -> 950.235 | Q19: =L19*(1+Assumptions!Q8) -> 154.39054 | R19: =M19*(1+Assumptions!R8) -> 267.57109 | S19: =N19*(1+Assumptions!S8) -> 297.29131 | T19: =O19*(1+Assumptions!T8) -> 307.00086 | U19: =SUM(Q19:T19) -> 1026.2538 | W19: Interest revenue (3 lines): ACTUALS for Q1 2025 (10-Q exact) and 2026Q1 (back-solved). 2026Q2-2028: grown at the same consolidated revenue growth rate as the four main segments (Assumptions row 8), for consistency with the guidance-midpoint calibration. In practice interest revenue may behave differently (it depends on rates and settlement-balance levels, not transaction volume), so this is a simplification -- but interest is now a small (~1%) and declining share of total revenue.
A20: Interest - Prepaid card services | B20: 182.661 | C20: 168.78 | D20: 187.527 | E20: 200.906 | F20: =SUM(B20:E20) -> 739.874 | G20: 107.875 | H20: =C20*(1+Assumptions!H8) -> 186.95666 | I20: =D20*(1+Assumptions!I8) -> 207.72261 | J20: =E20*(1+Assumptions!J8) -> 214.50622 | K20: =SUM(G20:J20) -> 717.06049 | L20: =G20*(1+Assumptions!L8) -> 116.505 | M20: =H20*(1+Assumptions!M8) -> 201.9132 | N20: =I20*(1+Assumptions!N8) -> 224.34042 | O20: =J20*(1+Assumptions!O8) -> 231.66671 | P20: =SUM(L20:O20) -> 774.42533 | Q20: =L20*(1+Assumptions!Q8) -> 125.8254 | R20: =M20*(1+Assumptions!R8) -> 218.06625 | S20: =N20*(1+Assumptions!S8) -> 242.28765 | T20: =O20*(1+Assumptions!T8) -> 250.20005 | U20: =SUM(Q20:T20) -> 836.37936
A21: Interest - Output Solutions | B21: 38.731 | C21: 35.788 | D21: 39.763 | E21: 42.6 | F21: =SUM(B21:E21) -> 156.882 | G21: 22.874 | H21: =C21*(1+Assumptions!H8) -> 39.642168 | I21: =D21*(1+Assumptions!I8) -> 44.045253 | J21: =E21*(1+Assumptions!J8) -> 45.483782 | K21: =SUM(G21:J21) -> 152.0452 | L21: =G21*(1+Assumptions!L8) -> 24.70392 | M21: =H21*(1+Assumptions!M8) -> 42.813541 | N21: =I21*(1+Assumptions!N8) -> 47.568874 | O21: =J21*(1+Assumptions!O8) -> 49.122485 | P21: =SUM(L21:O21) -> 164.20882 | Q21: =L21*(1+Assumptions!Q8) -> 26.680234 | R21: =M21*(1+Assumptions!R8) -> 46.238625 | S21: =N21*(1+Assumptions!S8) -> 51.374383 | T21: =O21*(1+Assumptions!T8) -> 53.052284 | U21: =SUM(Q21:T21) -> 177.34553 | W21: Interest revenue (3 lines): ACTUALS for Q1 2025 (10-Q exact: $224.1K / $182.7K / $38.7K) and 2026Q1 (back-solved from total revenue less the four segment lines above = $263.1K total, allocated using Q1 2025 proportions: ~85% ACH, ~13% prepaid, ~2% Output). Q2-Q4 2025 estimated similarly as part of the segment-allocation residual. 2026Q2-2028: held FLAT at the prior quarter's level (interest rates and settlement-balance levels assumed roughly stable; this is a small, declining share of total revenue, ~1% by 2026).
A22: TOTAL REVENUE | B22: =SUM(B14:B21) -> 22009.05 | C22: =SUM(C14:C21) -> 19960.99 | D22: =SUM(D14:D21) -> 21180.333 | E22: =SUM(E14:E21) -> 22240 | F22: =SUM(B22:E22) -> 85390.373 | G22: =SUM(G14:G21) -> 25465.776 | H22: =SUM(H14:H21) -> 22110.677 | I22: =SUM(I14:I21) -> 23461.337 | J22: =SUM(J14:J21) -> 23745.524 | K22: =SUM(G22:J22) -> 94783.314 | L22: =SUM(L14:L21) -> 27503.038 | M22: =SUM(M14:M21) -> 23879.531 | N22: =SUM(N14:N21) -> 25338.244 | O22: =SUM(O14:O21) -> 25645.166 | P22: =SUM(L22:O22) -> 102365.98 | Q22: =SUM(Q14:Q21) -> 29703.281 | R22: =SUM(R14:R21) -> 25789.894 | S22: =SUM(S14:S21) -> 27365.303 | T22: =SUM(T14:T21) -> 27696.779 | U22: =SUM(Q22:T22) -> 110555.26
A23: Total revenue growth % YoY | G23: =G22/B22-1 -> 0.1570593 | H23: =H22/C22-1 -> 0.10769442 | I23: =I22/D22-1 -> 0.10769442 | J23: =J22/E22-1 -> 0.067694423 | K23: =K22/F22-1 -> 0.11 | L23: =L22/G22-1 -> 0.08 | M23: =M22/H22-1 -> 0.08 | N23: =N22/I22-1 -> 0.08 | ... U23: =U22/P22-1 -> 0.08
A25: Segment Mix (% of Total Revenue)
A26: ACH & Complementary Services % | B26: =B14/B22 -> 0.22920194 | C26: =C14/C22 -> 0.26011856 | D26: =D14/D22 -> 0.27592895 | E26: =E14/E22 -> 0.27363575 | F26: =F14/F22 -> 0.25959211 | G26: =G14/G22 -> 0.24761256 | H26: =H14/H22 -> 0.26011856 | I26: =I14/I22 -> 0.27592895 | ... U26: =U14/U22 -> 0.26405839
A27: Credit Card % | B27: =B15/B22 -> 0.3579752 | C27: =C15/C22 -> 0.35293991 | D27: =D15/D22 -> 0.34708614 | E27: =E15/E22 -> 0.34172662 | F27: =F15/F22 -> 0.34986525 | G27: =G15/G22 -> 0.38054187 | H27: =H15/H22 -> 0.35293991 | I27: =I15/I22 -> 0.34708614 | ... U27: =U15/U22 -> 0.35609767
A28: Output Solutions % | B28: =B16/B22 -> 0.26047771 | C28: =C16/C22 -> 0.26537752 | D28: =D16/D22 -> 0.27787958 | E28: =E16/E22 -> 0.28352046 | F28: =F16/F22 -> 0.27194098 | G28: =G16/G22 -> 0.26789335 | H28: =H16/H22 -> 0.26537752 | I28: =I16/I22 -> 0.27787958 | ... U28: =U16/U22 -> 0.27369329
A29: Prepaid Card Services % | B29: =B17/B22 -> 0.13210252 | C29: =C17/C22 -> 0.10094058 | D29: =D17/D22 -> 0.077510349 | E29: =E17/E22 -> 0.079083813 | F29: =F17/F22 -> 0.097468177 | G29: =G17/G22 -> 0.093620159 | H29: =H17/H22 -> 0.10094058 | I29: =I17/I22 -> 0.077510349 | ... U29: =U17/U22 -> 0.087698534
A31: Note: Income Statement!row6 (Revenue) links directly to this tab's Total Revenue (row 22) for all periods.

Sheet Income Statement
A1: Usio, Inc. — Consolidated Income Statement (Quarterly)
A2: ($ in thousands, except per-share data)
A4: Fiscal Period | B4: 2025Q1A | C4: 2025Q2A | D4: 2025Q3A | E4: 2025Q4A | F4: FY2025A | G4: 2026Q1A | H4: 2026Q2E | I4: 2026Q3E | J4: 2026Q4E | K4: FY2026E | L4: 2027Q1E | M4: 2027Q2E | N4: 2027Q3E | O4: 2027Q4E | P4: FY2027E | Q4: 2028Q1E | R4: 2028Q2E | S4: 2028Q3E | T4: 2028Q4E | U4: FY2028E
A6: Revenue | B6: ='Revenue Build'!B22 -> 22009.05 | C6: ='Revenue Build'!C22 -> 19960.99 | D6: ='Revenue Build'!D22 -> 21180.333 | E6: ='Revenue Build'!E22 -> 22240 | F6: ='Revenue Build'!F22 -> 85390.373 | G6: ='Revenue Build'!G22 -> 25465.776 | H6: ='Revenue Build'!H22 -> 22110.677 | I6: ='Revenue Build'!I22 -> 23461.337 | ... U6: ='Revenue Build'!U22 -> 110555.26 | W6: 2025: exact quarterly revenue from 10-Qs (Q1-Q3) and 8-K 3/18/2026 (Q4 $22.24M). 2026Q1: $25,465,774 actual (10-Q, +15.7% YoY). 2026Q2-2028: prior-year-quarter x (1+YoY growth driver, Assumptions row 8), with 2026 calibrated to the 11% guidance midpoint (see Assumptions and Guidance & Street Recon tabs).
A7: Revenue growth % YoY | G7: =G6/B6-1 -> 0.1570593 | H7: =H6/C6-1 -> 0.10769442 | I7: =I6/D6-1 -> 0.10769442 | J7: =J6/E6-1 -> 0.067694423 | K7: =K6/F6-1 -> 0.11 | L7: =L6/G6-1 -> 0.08 | M7: =M6/H6-1 -> 0.08 | N7: =N6/I6-1 -> 0.08 | ... U7: =U6/P6-1 -> 0.08
A8: Gross Profit | B8: 4809.143 | C8: 5140.069 | D8: 4870.019 | E8: 4900 | F8: =SUM(B8:E8) -> 19719.231 | G8: 5136.883 | H8: =H6*Assumptions!H9 -> 4974.9024 | I8: =I6*Assumptions!I9 -> 5349.1848 | J8: =J6*Assumptions!J9 -> 5461.4705 | K8: =SUM(G8:J8) -> 20922.441 | L8: =L6*Assumptions!L9 -> 6188.1836 | M8: =M6*Assumptions!M9 -> 5372.8946 | N8: =N6*Assumptions!N9 -> 5701.1048 | O8: =O6*Assumptions!O9 -> 5770.1623 | P8: =SUM(L8:O8) -> 23032.345 | Q8: =Q6*Assumptions!Q9 -> 6683.2383 | R8: =R6*Assumptions!R9 -> 5802.7262 | S8: =S6*Assumptions!S9 -> 6157.1932 | T8: =T6*Assumptions!T9 -> 6231.7753 | U8: =SUM(Q8:T8) -> 24874.933 | W8: 2025 & 2026Q1: exact actuals from 10-Qs/8-K. 2026Q2-2028: Revenue x Gross margin % (Assumptions row 9).
A9: Gross margin % | B9: =B8/B6 -> 0.21850752 | C9: =C8/C6 -> 0.25750571 | D9: =D8/D6 -> 0.22993118 | E9: =E8/E6 -> 0.22032374 | F9: =F8/F6 -> 0.23093038 | G9: =G8/G6 -> 0.20171712 | H9: =H8/H6 -> 0.225 | I9: =I8/I6 -> 0.228 | ... U9: =U8/U6 -> 0.225
A10: Cost of services (implied) | B10: =B6-B8 -> 17199.907 | C10: =C6-C8 -> 14820.921 | D10: =D6-D8 -> 16310.314 | E10: =E6-E8 -> 17340 | F10: =SUM(B10:E10) -> 65671.142 | G10: =G6-G8 -> 20328.893 | H10: =H6-H8 -> 17135.775 | I10: =I6-I8 -> 18112.152 | J10: =J6-J8 -> 18284.053 | K10: =SUM(G10:J10) -> 73860.873 | L10: =L6-L8 -> 21314.855 | M10: =M6-M8 -> 18506.637 | N10: =N6-N8 -> 19637.139 | O10: =O6-O8 -> 19875.004 | P10: =SUM(L10:O10) -> 79333.634 | Q10: =Q6-Q8 -> 23020.043 | R10: =R6-R8 -> 19987.168 | S10: =S6-S8 -> 21208.11 | T10: =T6-T8 -> 21465.004 | U10: =SUM(Q10:T10) -> 85680.325
A12: Operating Expenses
A13: Stock-based compensation | B13: 410.062 | C13: 434.255 | D13: 399.582 | E13: 315.63 | F13: =SUM(B13:E13) -> 1559.529 | G13: 329.284 | H13: =H6*Assumptions!H10 -> 287.4388 | I13: =I6*Assumptions!I10 -> 304.99738 | J13: =J6*Assumptions!J10 -> 308.69181 | K13: =SUM(G13:J13) -> 1230.412 | L13: =L6*Assumptions!L10 -> 357.5395 | M13: =M6*Assumptions!M10 -> 310.43391 | N13: =N6*Assumptions!N10 -> 329.39717 | O13: =O6*Assumptions!O10 -> 333.38716 | P13: =SUM(L13:O13) -> 1330.7577 | Q13: =Q6*Assumptions!Q10 -> 386.14265 | R13: =R6*Assumptions!R10 -> 335.26862 | S13: =S6*Assumptions!S10 -> 355.74894 | T13: =T6*Assumptions!T10 -> 360.05813 | U13: =SUM(Q13:T13) -> 1437.2183 | W13: 2025 & 2026Q1: exact actuals (10-Qs). 2026Q2-2028: Revenue x SBC % (Assumptions row 10).
A14: Other SG&A | B14: 4142.895 | C14: 3793.868 | D14: 4102.18 | E14: 3054.795 | F14: =SUM(B14:E14) -> 15093.738 | G14: 4356.142 | H14: =H6*Assumptions!H11 -> 3648.2618 | I14: =I6*Assumptions!I11 -> 3871.1206 | J14: =J6*Assumptions!J11 -> 3918.0115 | K14: =SUM(G14:J14) -> 15793.536 | L14: =L6*Assumptions!L11 -> 4538.0013 | M14: =M6*Assumptions!M11 -> 3940.1227 | N14: =N6*Assumptions!N11 -> 4180.8102 | O14: =O6*Assumptions!O11 -> 4231.4524 | P14: =SUM(L14:O14) -> 16890.387 | Q14: =Q6*Assumptions!Q11 -> 4901.0414 | R14: =R6*Assumptions!R11 -> 4255.3325 | S14: =S6*Assumptions!S11 -> 4515.275 | T14: =T6*Assumptions!T11 -> 4569.9686 | U14: =SUM(Q14:T14) -> 18241.617 | W14: 2025: Q1-Q3 exact from 10-Qs; Q4 back-solved so FY2025 SBC+Other SG&A+D&A = $18.4M (10-K) using Q1-Q3 average proportions. 2026Q1: exact actual ($4,356,142). 2026Q2-2028: Revenue x Other SG&A % (Assumptions row 11).
A15: Depreciation & amortization | B15: 495.77 | C15: 464.599 | D15: 432.846 | E15: 353.518 | F15: =SUM(B15:E15) -> 1746.733 | G15: 225.745 | H15: =H6*Assumptions!H12 -> 243.21745 | I15: =I6*Assumptions!I12 -> 258.0747 | J15: =J6*Assumptions!J12 -> 261.20076 | K15: =SUM(G15:J15) -> 988.23792 | L15: =L6*Assumptions!L12 -> 302.53342 | M15: =M6*Assumptions!M12 -> 262.67485 | N15: =N6*Assumptions!N12 -> 278.72068 | O15: =O6*Assumptions!O12 -> 282.09682 | P15: =SUM(L15:O15) -> 1126.0258 | Q15: =Q6*Assumptions!Q12 -> 326.73609 | R15: =R6*Assumptions!R12 -> 283.68883 | S15: =S6*Assumptions!S12 -> 301.01833 | T15: =T6*Assumptions!T12 -> 304.66457 | U15: =SUM(Q15:T15) -> 1216.1078 | W15: 2025 & 2026Q1: exact actuals. 2026Q2-2028: Revenue x D&A % (Assumptions row 12).
A16: Total Operating Expenses | B16: =SUM(B13:B15) -> 5048.727 | C16: =SUM(C13:C15) -> 4692.722 | D16: =SUM(D13:D15) -> 4934.608 | E16: =SUM(E13:E15) -> 3723.943 | F16: =SUM(B16:E16) -> 18400 | G16: =SUM(G13:G15) -> 4911.171 | H16: =SUM(H13:H15) -> 4178.918 | I16: =SUM(I13:I15) -> 4434.1926 | J16: =SUM(J13:J15) -> 4487.904 | K16: =SUM(G16:J16) -> 18012.186 | L16: =SUM(L13:L15) -> 5198.0742 | M16: =SUM(M13:M15) -> 4513.2315 | N16: =SUM(N13:N15) -> 4788.9281 | O16: =SUM(O13:O15) -> 4846.9364 | P16: =SUM(L16:O16) -> 19347.17 | Q16: =SUM(Q13:Q15) -> 5613.9201 | R16: =SUM(R13:R15) -> 4874.29 | S16: =SUM(S13:S15) -> 5172.0423 | T16: =SUM(T13:T15) -> 5234.6913 | U16: =SUM(Q16:T16) -> 20894.944
A18: Operating Income (Loss) | B18: =B8-B16 -> -239.584 | C18: =C8-C16 -> 447.347 | D18: =D8-D16 -> -64.589 | E18: =E8-E16 -> 1176.057 | F18: =SUM(B18:E18) -> 1319.231 | G18: =G8-G16 -> 225.712 | H18: =H8-H16 -> 795.98438 | I18: =I8-I16 -> 914.99213 | J18: =J8-J16 -> 973.56648 | K18: =SUM(G18:J18) -> 2910.255 | L18: =L8-L16 -> 990.10937 | M18: =M8-M16 -> 859.66313 | N18: =N8-N16 -> 912.17677 | O18: =O8-O16 -> 923.22597 | P18: =SUM(L18:O18) -> 3685.1752 | Q18: =Q8-Q16 -> 1069.3181 | R18: =R8-R16 -> 928.43618 | S18: =S8-S16 -> 985.15091 | T18: =T8-T16 -> 997.08405 | U18: =SUM(Q18:T18) -> 3979.9893
A19: Operating margin % | B19: =B18/B6 -> -0.010885704 | C19: =C18/C6 -> 0.022411063 | D19: =D18/D6 -> -0.0030494799 | E19: =E18/E6 -> 0.052880261 | F19: =F18/F6 -> 0.015449411 | G19: =G18/G6 -> 0.0088633466 | H19: =H18/H6 -> 0.036 | I19: =I18/I6 -> 0.039 | ... U19: =U18/U6 -> 0.036
A20: Other income (loss), net | B20: 4.614 | C20: -813.997 | D20: -335.411 | E20: -2676.057 | F20: =SUM(B20:E20) -> -3820.851 | G20: 137.33 | H20: =Assumptions!H14 -> 137 | I20: =Assumptions!I14 -> 137 | J20: =Assumptions!J14 -> 137 | K20: =SUM(G20:J20) -> 548.33 | L20: =Assumptions!L14 -> 137 | M20: =Assumptions!M14 -> 137 | N20: =Assumptions!N14 -> 137 | O20: =Assumptions!O14 -> 137 | P20: =SUM(L20:O20) -> 548 | Q20: =Assumptions!Q14 -> 137 | R20: =Assumptions!R14 -> 137 | S20: =Assumptions!S14 -> 137 | T20: =Assumptions!T14 -> 137 | U20: =SUM(Q20:T20) -> 548 | W20: 2025 Q1-Q4: for 2025 this row is a single below-the-line plug = (reported quarterly net income) - (modeled operating income), so each quarter ties exactly to its disclosed net income/loss (Q1 $(0.235M), Q2 $(0.367M), Q3 $(0.4M), Q4 $(1.5M)). The large Q4 item (~$(2.68M)) likely reflects a tax valuation-allowance adjustment and/or acquisition-related charges not separately disclosed in the retrieved press release. 2026Q1: exact actual (interest income $91.5K - interest expense $22.8K + other income $68.7K = $137.3K, pre-tax). 2026Q2-2028: Assumptions row 14 ($137K/qtr).
A21: Pre-tax Income (Loss) | B21: =B18+B20 -> -234.97 | C21: =C18+C20 -> -366.65 | D21: =D18+D20 -> -400 | E21: =E18+E20 -> -1500 | F21: =SUM(B21:E21) -> -2501.62 | G21: =G18+G20 -> 363.042 | H21: =H18+H20 -> 932.98438 | I21: =I18+I20 -> 1051.9921 | J21: =J18+J20 -> 1110.5665 | K21: =SUM(G21:J21) -> 3458.585 | L21: =L18+L20 -> 1127.1094 | M21: =M18+M20 -> 996.66313 | N21: =N18+N20 -> 1049.1768 | O21: =O18+O20 -> 1060.226 | P21: =SUM(L21:O21) -> 4233.1752 | Q21: =Q18+Q20 -> 1206.3181 | R21: =R18+R20 -> 1065.4362 | S21: =S18+S20 -> 1122.1509 | T21: =T18+T20 -> 1134.084 | U21: =SUM(Q21:T21) -> 4527.9893
A22: Income tax expense (benefit) | B22: 0 | C22: 0 | D22: 0 | E22: 0 | F22: =SUM(B22:E22) -> 0 | G22: 171.874 | H22: =H21*Assumptions!H13 -> 279.89531 | I22: =I21*Assumptions!I13 -> 315.59764 | J22: =J21*Assumptions!J13 -> 333.16994 | K22: =SUM(G22:J22) -> 1100.5369 | L22: =L21*Assumptions!L13 -> 338.13281 | M22: =M21*Assumptions!M13 -> 298.99894 | N22: =N21*Assumptions!N13 -> 314.75303 | O22: =O21*Assumptions!O13 -> 318.06779 | P22: =SUM(L22:O22) -> 1269.9526 | Q22: =Q21*Assumptions!Q13 -> 361.89544 | R22: =R21*Assumptions!R13 -> 319.63086 | S22: =S21*Assumptions!S13 -> 336.64527 | T22: =T21*Assumptions!T13 -> 340.22521 | U22: =SUM(Q22:T22) -> 1358.3968 | W22: 2025 Q1-Q4: set to zero — actual tax effects are embedded in the 'Other income, net' plug above (row 16) so quarterly net income ties to disclosed actuals without double-counting. 2026Q1: exact actual ($171,874 = federal $67,084 + state $104,790). 2026Q2-2028: Pre-tax income x Effective tax rate (Assumptions row 13).
A24: Net Income (Loss) | B24: =B21-B22 -> -234.97 | C24: =C21-C22 -> -366.65 | D24: =D21-D22 -> -400 | E24: =E21-E22 -> -1500 | F24: =SUM(B24:E24) -> -2501.62 | G24: =G21-G22 -> 191.168 | H24: =H21-H22 -> 653.08907 | I24: =I21-I22 -> 736.39449 | J24: =J21-J22 -> 777.39654 | K24: =SUM(G24:J24) -> 2358.0481 | L24: =L21-L22 -> 788.97656 | M24: =M21-M22 -> 697.66419 | N24: =N21-N22 -> 734.42374 | O24: =O21-O22 -> 742.15818 | P24: =SUM(L24:O24) -> 2963.2227 | Q24: =Q21-Q22 -> 844.42268 | R24: =R21-R22 -> 745.80533 | S24: =S21-S22 -> 785.50564 | T24: =T21-T22 -> 793.85883 | U24: =SUM(Q24:T24) -> 3169.5925
A25: Net margin % | B25: =B24/B6 -> -0.010676063 | C25: =C24/C6 -> -0.018368327 | D25: =D24/D6 -> -0.018885444 | E25: =E24/E6 -> -0.067446043 | F25: =F24/F6 -> -0.029296277 | G25: =G24/G6 -> 0.0075068594 | H25: =H24/H6 -> 0.029537271 | I25: =I24/I6 -> 0.031387576 | ... U25: =U24/U6 -> 0.028669758
A27: Diluted weighted avg. shares (000) | B27: 26615.947 | C27: 26850 | D27: 27000 | E27: 27300 | F27: =AVERAGE(B27:E27) -> 26941.487 | G27: 27748.037 | H27: =Assumptions!H15 -> 27800 | I27: =Assumptions!I15 -> 27800 | J27: =Assumptions!J15 -> 27800 | K27: =AVERAGE(G27:J27) -> 27787.009 | L27: =Assumptions!L15 -> 27800 | M27: =Assumptions!M15 -> 27800 | N27: =Assumptions!N15 -> 27800 | O27: =Assumptions!O15 -> 27800 | P27: =AVERAGE(L27:O27) -> 27800 | Q27: =Assumptions!Q15 -> 27800 | R27: =Assumptions!R15 -> 27800 | S27: =Assumptions!S15 -> 27800 | T27: =Assumptions!T15 -> 27800 | U27: =AVERAGE(Q27:T27) -> 27800 | W27: 2025Q1 and 2026Q1: exact actuals from 10-Qs (26,615,947 and 27,748,037). 2025Q2-Q4: interpolated (consistent with FY2025 weighted avg of ~27.45M reported in earlier filings). 2026Q2-2028: Assumptions row 15.
A28: Diluted EPS | B28: =B24/B27 -> -0.0088281661 | C28: =C24/C27 -> -0.013655493 | D28: =D24/D27 -> -0.014814815 | E28: =E24/E27 -> -0.054945055 | F28: =F24/F27 -> -0.092853821 | G28: =G24/G27 -> 0.0068894243 | H28: =H24/H27 -> 0.023492413 | I28: =I24/I27 -> 0.026489011 | ... U28: =U24/U27 -> 0.11401412
A30: Memo: EBITDA & Adj. EBITDA
A31: EBITDA (Op. Income + D&A) | B31: =B18+B15 -> 256.186 | C31: =C18+C15 -> 911.946 | D31: =D18+D15 -> 368.257 | E31: =E18+E15 -> 1529.575 | F31: =SUM(B31:E31) -> 3065.964 | G31: =G18+G15 -> 451.457 | H31: =H18+H15 -> 1039.2018 | I31: =I18+I15 -> 1173.0668 | J31: =J18+J15 -> 1234.7672 | K31: =SUM(G31:J31) -> 3898.4929 | L31: =L18+L15 -> 1292.6428 | M31: =M18+M15 -> 1122.338 | N31: =N18+N15 -> 1190.8975 | O31: =O18+O15 -> 1205.3228 | P31: =SUM(L31:O31) -> 4811.201 | Q31: =Q18+Q15 -> 1396.0542 | R31: =R18+R15 -> 1212.125 | S31: =S18+S15 -> 1286.1692 | T31: =T18+T15 -> 1301.7486 | U31: =SUM(Q31:T31) -> 5196.0971
A32: Adj. EBITDA (EBITDA + SBC) | B32: =B31+B13 -> 666.248 | C32: =C31+C13 -> 1346.201 | D32: =D31+D13 -> 767.839 | E32: =E31+E13 -> 1845.205 | F32: =SUM(B32:E32) -> 4625.493 | G32: =G31+G13 -> 780.741 | H32: =H31+H13 -> 1326.6406 | I32: =I31+I13 -> 1478.0642 | J32: =J31+J13 -> 1543.4591 | K32: =SUM(G32:J32) -> 5128.9049 | L32: =L31+L13 -> 1650.1823 | M32: =M31+M13 -> 1432.7719 | N32: =N31+N13 -> 1520.2946 | O32: =O31+O13 -> 1538.71 | P32: =SUM(L32:O32) -> 6141.9587 | Q32: =Q31+Q13 -> 1782.1969 | R32: =R31+R13 -> 1547.3936 | S32: =S31+S13 -> 1641.9182 | T32: =T31+T13 -> 1661.8067 | U32: =SUM(Q32:T32) -> 6633.3154 | W32: Model proxy for management's non-GAAP 'Adjusted EBITDA' (EBITDA + stock-based compensation). Company-reported Adj. EBITDA: FY2025 $1.3M, FY2024 $2.9M, 2026Q1 $0.8M (beat consensus by 12% per 8-K 5/13/2026). Compare to this row for a sanity check — see Guidance & Street Recon tab.
A33: Adj. EBITDA margin % | B33: =B32/B6 -> 0.030271547 | C33: =C32/C6 -> 0.067441595 | D33: =D32/D6 -> 0.036252452 | E33: =E32/E6 -> 0.082967851 | F33: =F32/F6 -> 0.054168788 | G33: =G32/G6 -> 0.030658441 | H33: =H32/H6 -> 0.06 | I33: =I32/I6 -> 0.063 | ... U33: =U32/U6 -> 0.06

Sheet Balance Sheet
A1: Usio, Inc. — Consolidated Balance Sheet (Quarterly, period-end)
A2: ($ in thousands). Annual columns (F,K,P,U) = same as Q4 of that year (year-end balance sheet), shown for reference.
A4: Period-end | B4: 2025Q1A | C4: 2025Q2A | D4: 2025Q3A | E4: 2025Q4A | F4: FY2025A | G4: 2026Q1A | H4: 2026Q2E | I4: 2026Q3E | J4: 2026Q4E | K4: FY2026E | L4: 2027Q1E | M4: 2027Q2E | N4: 2027Q3E | O4: 2027Q4E | P4: FY2027E | Q4: 2028Q1E | R4: 2028Q2E | S4: 2028Q3E | T4: 2028Q4E | U4: FY2028E
A6: ASSETS
A7: Current Assets
A8: Cash & cash equivalents | B8: =7500+($E8-7500)/4*1 -> 7483.5127 | C8: =7500+($E8-7500)/4*2 -> 7467.0255 | D8: =7500+($E8-7500)/4*3 -> 7450.5382 | E8: 7434.051 | F8: =E8 -> 7434.051 | G8: 7728.795 | H8: ='Cash Flow Statement'!H21 -> 8874.1032 | I8: ='Cash Flow Statement'!I21 -> 9843.0558 | J8: ='Cash Flow Statement'!J21 -> 10865.134 | K8: =J8 -> 10865.134 | L8: ='Cash Flow Statement'!L21 -> 11968.477 | M8: ='Cash Flow Statement'!M21 -> 12846.315 | N8: ='Cash Flow Statement'!N21 -> 13835.156 | O8: ='Cash Flow Statement'!O21 -> 14826.707 | P8: =O8 -> 14826.707 | Q8: ='Cash Flow Statement'!Q21 -> 16019.779 | R8: ='Cash Flow Statement'!R21 -> 16978.606 | S8: ='Cash Flow Statement'!S21 -> 18056.782 | T8: ='Cash Flow Statement'!T21 -> 19137.379 | U8: =T8 -> 19137.379 | W8: ACTUALS: $7,434,051 at 12/31/2025 and $7,728,795 at 3/31/2026 (Q1 2026 10-Q balance sheet — note this differs slightly from the $7.5M figure cited in the earnings-call transcript). 2025 Q1-Q3 linearly interpolated from FY2024 year-end cash ($7.5M, 10-K) to the FY2025 actual. 2026Q2-2028: linked to Cash Flow Statement ending cash.
A9: Accounts receivable, net | B9: ='Income Statement'!B6/91*19 -> 4595.2962 | C9: ='Income Statement'!C6/91*19 -> 4167.6792 | D9: ='Income Statement'!D6/91*19 -> 4422.2673 | E9: 5274.586 | F9: =E9 -> 5274.586 | G9: 5418.653 | H9: ='Income Statement'!H6/91*Assumptions!H18 -> 4616.515 | I9: ='Income Statement'!I6/91*Assumptions!I18 -> 4898.5209 | J9: ='Income Statement'!J6/91*Assumptions!J18 -> 4957.8567 | K9: =J9 -> 4957.8567 | L9: ='Income Statement'!L6/91*Assumptions!L18 -> 5742.3926 | M9: ='Income Statement'!M6/91*Assumptions!M18 -> 4985.8362 | N9: ='Income Statement'!N6/91*Assumptions!N18 -> 5290.4025 | O9: ='Income Statement'!O6/91*Assumptions!O18 -> 5354.4852 | P9: =O9 -> 5354.4852 | Q9: ='Income Statement'!Q6/91*Assumptions!Q18 -> 6201.784 | R9: ='Income Statement'!R6/91*Assumptions!R18 -> 5384.7031 | S9: ='Income Statement'!S6/91*Assumptions!S18 -> 5713.6347 | T9: ='Income Statement'!T6/91*Assumptions!T18 -> 5782.844 | U9: =T9 -> 5782.844 | W9: ACTUALS: $5,274,586 (12/31/2025) and $5,418,653 (3/31/2026), both per Q1 2026 10-Q balance sheet. 2025 Q1-Q3 estimated via Revenue/91 days x 19-day DSO (consistent with the actual ratios at quarter-ends). 2026Q2-2028: Revenue/91 x DSO (Assumptions row 18).
A10: Settlement processing assets | B10: ='Income Statement'!B6*2.8 -> 61625.34 | C10: ='Income Statement'!C6*2.8 -> 55890.772 | D10: ='Income Statement'!D6*2.8 -> 59304.932 | E10: 74180.475 | F10: =E10 -> 74180.475 | G10: 69522.444 | H10: ='Income Statement'!H6*Assumptions!H20 -> 61909.896 | I10: ='Income Statement'!I6*Assumptions!I20 -> 65691.743 | J10: ='Income Statement'!J6*Assumptions!J20 -> 66487.467 | K10: =J10 -> 66487.467 | L10: ='Income Statement'!L6*Assumptions!L20 -> 77008.507 | M10: ='Income Statement'!M6*Assumptions!M20 -> 66862.688 | N10: ='Income Statement'!N6*Assumptions!N20 -> 70947.082 | O10: ='Income Statement'!O6*Assumptions!O20 -> 71806.464 | P10: =O10 -> 71806.464 | Q10: ='Income Statement'!Q6*Assumptions!Q20 -> 83169.187 | R10: ='Income Statement'!R6*Assumptions!R20 -> 72211.703 | S10: ='Income Statement'!S6*Assumptions!S20 -> 76622.849 | T10: ='Income Statement'!T6*Assumptions!T20 -> 77550.982 | U10: =T10 -> 77550.982 | W10: ACTUALS: $74,180,475 (12/31/2025) and $69,522,444 (3/31/2026), EXACTLY equal to settlement processing OBLIGATIONS on the liability side (a 1:1 pass-through), per Q1 2026 10-Q. 2025 Q1-Q3 estimated at 2.80x quarterly revenue (Assumptions row 20). 2026Q2-2028 same driver.
A11: Prepaid card load assets | B11: ='Income Statement'!B6*0.65 -> 14305.882 | C11: ='Income Statement'!C6*0.65 -> 12974.644 | D11: ='Income Statement'!D6*0.65 -> 13767.216 | E11: 27623.728 | F11: =E11 -> 27623.728 | G11: 15466.828 | H11: ='Income Statement'!H6*Assumptions!H21 -> 14371.94 | I11: ='Income Statement'!I6*Assumptions!I21 -> 15249.869 | J11: ='Income Statement'!J6*Assumptions!J21 -> 15434.591 | K11: =J11 -> 15434.591 | L11: ='Income Statement'!L6*Assumptions!L21 -> 17876.975 | M11: ='Income Statement'!M6*Assumptions!M21 -> 15521.695 | N11: ='Income Statement'!N6*Assumptions!N21 -> 16469.858 | O11: ='Income Statement'!O6*Assumptions!O21 -> 16669.358 | P11: =O11 -> 16669.358 | Q11: ='Income Statement'!Q6*Assumptions!Q21 -> 19307.133 | R11: ='Income Statement'!R6*Assumptions!R21 -> 16763.431 | S11: ='Income Statement'!S6*Assumptions!S21 -> 17787.447 | T11: ='Income Statement'!T6*Assumptions!T21 -> 18002.906 | U11: =T11 -> 18002.906 | W11: ACTUALS: $27,623,728 (12/31/2025) and $15,466,828 (3/31/2026), EXACTLY equal to prepaid card load OBLIGATIONS (1:1 pass-through), per Q1 2026 10-Q. The sharp Q4->Q1 decline reflects seasonal holiday gift-card loads unwinding. 2025 Q1-Q3 estimated at 0.65x quarterly revenue (Assumptions row 21, a non-seasonal baseline). 2026Q2-2028 same driver.
A12: Customer deposits (asset) | B12: ='Income Statement'!B6*0.1 -> 2200.905 | C12: ='Income Statement'!C6*0.1 -> 1996.099 | D12: ='Income Statement'!D6*0.1 -> 2118.0333 | E12: 2281.22 | F12: =E12 -> 2281.22 | G12: 2239.829 | H12: ='Income Statement'!H6*Assumptions!H22 -> 2211.0677 | I12: ='Income Statement'!I6*Assumptions!I22 -> 2346.1337 | J12: ='Income Statement'!J6*Assumptions!J22 -> 2374.5524 | K12: =J12 -> 2374.5524 | L12: ='Income Statement'!L6*Assumptions!L22 -> 2750.3038 | M12: ='Income Statement'!M6*Assumptions!M22 -> 2387.9531 | N12: ='Income Statement'!N6*Assumptions!N22 -> 2533.8244 | O12: ='Income Statement'!O6*Assumptions!O22 -> 2564.5166 | P12: =O12 -> 2564.5166 | Q12: ='Income Statement'!Q6*Assumptions!Q22 -> 2970.3281 | R12: ='Income Statement'!R6*Assumptions!R22 -> 2578.9894 | S12: ='Income Statement'!S6*Assumptions!S22 -> 2736.5303 | T12: ='Income Statement'!T6*Assumptions!T22 -> 2769.6779 | U12: =T12 -> 2769.6779 | W12: ACTUALS: $2,281,220 (12/31/2025), $2,239,829 (3/31/2026), per Q1 2026 10-Q (also mirrors the liability side). Driver = Revenue x 0.10x (Assumptions row 22).
A13: Inventory | B13: =$E$13 -> 461.675 | C13: =$E$13 -> 461.675 | D13: =$E$13 -> 461.675 | E13: 461.675 | F13: =E13 -> 461.675 | G13: 392.873 | H13: =G13 -> 392.873 | I13: =H13 -> 392.873 | J13: =I13 -> 392.873 | K13: =J13 -> 392.873 | L13: =K13 -> 392.873 | M13: =L13 -> 392.873 | N13: =M13 -> 392.873 | O13: =N13 -> 392.873 | ... U13: =T13 -> 392.873 | W13: ACTUALS: $461,675 (12/31/2025), $392,873 (3/31/2026), per Q1 2026 10-Q (Output Solutions print/mail supplies inventory). Held flat going forward absent a specific driver.
A14: Merchant reserves | B14: ='Income Statement'!B6*0.2 -> 4401.81 | C14: ='Income Statement'!C6*0.2 -> 3992.198 | D14: ='Income Statement'!D6*0.2 -> 4236.0666 | E14: 4795.537 | F14: =E14 -> 4795.537 | G14: 4617.537 | H14: ='Income Statement'!H6*Assumptions!H23 -> 4422.1355 | I14: ='Income Statement'!I6*Assumptions!I23 -> 4692.2673 | J14: ='Income Statement'!J6*Assumptions!J23 -> 4749.1048 | K14: =J14 -> 4749.1048 | L14: ='Income Statement'!L6*Assumptions!L23 -> 5500.6076 | M14: ='Income Statement'!M6*Assumptions!M23 -> 4775.9063 | N14: ='Income Statement'!N6*Assumptions!N23 -> 5067.6487 | O14: ='Income Statement'!O6*Assumptions!O23 -> 5129.0332 | P14: =O14 -> 5129.0332 | Q14: ='Income Statement'!Q6*Assumptions!Q23 -> 5940.6562 | R14: ='Income Statement'!R6*Assumptions!R23 -> 5157.9788 | S14: ='Income Statement'!S6*Assumptions!S23 -> 5473.0606 | T14: ='Income Statement'!T6*Assumptions!T23 -> 5539.3558 | U14: =T14 -> 5539.3558 | W14: ACTUALS: $4,795,537 (12/31/2025), $4,617,537 (3/31/2026), per Q1 2026 10-Q. Driver = Revenue x 0.20x (Assumptions row 23).
A15: Prepaid expenses & other current | B15: =$E$15 -> 1359.382 | C15: =$E$15 -> 1359.382 | D15: =$E$15 -> 1359.382 | E15: 1359.382 | F15: =E15 -> 1359.382 | G15: 1903.69 | H15: =G15 -> 1903.69 | I15: =H15 -> 1903.69 | J15: =I15 -> 1903.69 | K15: =J15 -> 1903.69 | L15: =K15 -> 1903.69 | M15: =L15 -> 1903.69 | N15: =M15 -> 1903.69 | O15: =N15 -> 1903.69 | ... U15: =T15 -> 1903.69 | W15: ACTUALS: $1,359,382 (12/31/2025), $1,903,690 (3/31/2026), per Q1 2026 10-Q. Held flat at the 3/31/26 level for projections absent a specific driver.
A16: Total Current Assets | B16: =SUM(B8:B15) -> 96433.803 | C16: =SUM(C8:C15) -> 88309.474 | D16: =SUM(D8:D15) -> 93120.111 | E16: =SUM(E8:E15) -> 123410.65 | F16: =SUM(F8:F15) -> 123410.65 | G16: =SUM(G8:G15) -> 107290.65 | H16: =SUM(H8:H15) -> 98702.221 | I16: =SUM(I8:I15) -> 105018.15 | ... U16: =SUM(U8:U15) -> 131079.71
A18: Non-Current Assets
A19: Property & equipment, net | B19: =$E$19 -> 4157.393 | C19: =$E$19 -> 4157.393 | D19: =$E$19 -> 4157.393 | E19: 4157.393 | F19: =E19 -> 4157.393 | G19: 4545.252 | H19: =G19+'Income Statement'!H6*Assumptions!H24-'Income Statement'!H15 -> 4744.2481 | I19: =H19+'Income Statement'!I6*Assumptions!I24-'Income Statement'!I15 -> 4955.4001 | J19: =I19+'Income Statement'!J6*Assumptions!J24-'Income Statement'!J15 -> 5169.1098 | K19: =J19 -> 5169.1098 | L19: =K19+'Income Statement'!L6*Assumptions!L24-'Income Statement'!L15 -> 5416.6372 | M19: =L19+'Income Statement'!M6*Assumptions!M24-'Income Statement'!M15 -> 5631.553 | N19: =M19+'Income Statement'!N6*Assumptions!N24-'Income Statement'!N15 -> 5859.5972 | O19: =N19+'Income Statement'!O6*Assumptions!O24-'Income Statement'!O15 -> 6090.4037 | P19: =O19 -> 6090.4037 | Q19: =P19+'Income Statement'!Q6*Assumptions!Q24-'Income Statement'!Q15 -> 6357.7332 | R19: =Q19+'Income Statement'!R6*Assumptions!R24-'Income Statement'!R15 -> 6589.8422 | S19: =R19+'Income Statement'!S6*Assumptions!S24-'Income Statement'!S15 -> 6836.13 | T19: =S19+'Income Statement'!T6*Assumptions!T24-'Income Statement'!T15 -> 7085.401 | U19: =T19 -> 7085.401 | W19: ACTUALS: $4,157,393 (12/31/2025), $4,545,252 (3/31/2026), per Q1 2026 10-Q (the increase reflects the new printer installation per 10-K). 2026Q2-2028: prior + (Revenue x Capex% driver, Assumptions row 24) - D&A.
A20: Intangibles, net | B20: =$E$20 -> 9.759 | C20: =$E$20 -> 9.759 | D20: =$E$20 -> 9.759 | E20: 9.759 | F20: =E20 -> 9.759 | G20: 9.759 | H20: =G20 -> 9.759 | I20: =H20 -> 9.759 | J20: =I20 -> 9.759 | K20: =J20 -> 9.759 | L20: =K20 -> 9.759 | M20: =L20 -> 9.759 | N20: =M20 -> 9.759 | O20: =N20 -> 9.759 | ... U20: =T20 -> 9.759 | W20: ACTUALS: $9,759, unchanged 12/31/2025 to 3/31/2026 (nearly fully amortized per 10-K). Held flat.
A21: Deferred tax asset, net | B21: =$E$21 -> 4526.228 | C21: =$E$21 -> 4526.228 | D21: =$E$21 -> 4526.228 | E21: 4526.228 | F21: =E21 -> 4526.228 | G21: 4459.144 | H21: =MAX(0,G21-'Income Statement'!H22) -> 4179.2487 | I21: =MAX(0,H21-'Income Statement'!I22) -> 3863.651 | J21: =MAX(0,I21-'Income Statement'!J22) -> 3530.4811 | K21: =J21 -> 3530.4811 | L21: =MAX(0,K21-'Income Statement'!L22) -> 3192.3483 | M21: =MAX(0,L21-'Income Statement'!M22) -> 2893.3493 | N21: =MAX(0,M21-'Income Statement'!N22) -> 2578.5963 | O21: =MAX(0,N21-'Income Statement'!O22) -> 2260.5285 | P21: =O21 -> 2260.5285 | Q21: =MAX(0,P21-'Income Statement'!Q22) -> 1898.6331 | R21: =MAX(0,Q21-'Income Statement'!R22) -> 1579.0022 | S21: =MAX(0,R21-'Income Statement'!S22) -> 1242.357 | T21: =MAX(0,S21-'Income Statement'!T22) -> 902.13175 | U21: =T21 -> 902.13175 | W21: ACTUALS: $4,526,228 (12/31/2025), $4,459,144 (3/31/2026). 2026Q2-2028: prior balance less modeled income tax expense (NOL utilization), floored at zero.
A22: Operating lease ROU assets | B22: =$E$22 -> 2423.231 | C22: =$E$22 -> 2423.231 | D22: =$E$22 -> 2423.231 | E22: 2423.231 | F22: =E22 -> 2423.231 | G22: 3524.65 | H22: =G22+(H31-G31)+(H41-G41) -> 3461.2648 | I22: =H22+(I31-H31)+(I41-H41) -> 3399.0717 | J22: =I22+(J31-I31)+(J41-I41) -> 3338.0475 | K22: =J22 -> 3338.0475 | L22: =K22+(L31-K31)+(L41-K41) -> 3278.1696 | M22: =L22+(M31-L31)+(M41-L41) -> 3219.4159 | N22: =M22+(N31-M31)+(N41-M41) -> 3161.7645 | O22: =N22+(O31-N31)+(O41-N41) -> 3105.1942 | P22: =O22 -> 3105.1942 | Q22: =P22+(Q31-P31)+(Q41-P41) -> 3049.6841 | R22: =Q22+(R31-Q31)+(R41-Q41) -> 2995.2136 | S22: =R22+(S31-R31)+(S41-R41) -> 2941.7627 | T22: =S22+(T31-S31)+(T41-S41) -> 2889.3118 | U22: =T22 -> 2889.3118 | W22: ACTUALS: $2,423,231 (12/31/2025), $3,524,650 (3/31/2026) — increase reflects new lease(s) per 10-Q. 2026Q2-2028: amortizing ~3%/qtr absent further lease additions.
A23: Other non-current assets | B23: =$E$23 -> 362.949 | C23: =$E$23 -> 362.949 | D23: =$E$23 -> 362.949 | E23: 362.949 | F23: =E23 -> 362.949 | G23: 362.949 | H23: =G23 -> 362.949 | I23: =H23 -> 362.949 | J23: =I23 -> 362.949 | K23: =J23 -> 362.949 | L23: =K23 -> 362.949 | M23: =L23 -> 362.949 | N23: =M23 -> 362.949 | O23: =N23 -> 362.949 | ... U23: =T23 -> 362.949 | W23: ACTUALS: $362,949, unchanged 12/31/2025 to 3/31/2026. Held flat.
A24: Total Non-Current Assets | B24: =SUM(B19:B23) -> 11479.56 | C24: =SUM(C19:C23) -> 11479.56 | D24: =SUM(D19:D23) -> 11479.56 | E24: =SUM(E19:E23) -> 11479.56 | F24: =SUM(F19:F23) -> 11479.56 | G24: =SUM(G19:G23) -> 12901.754 | H24: =SUM(H19:H23) -> 12757.47 | I24: =SUM(I19:I23) -> 12590.831 | ... U24: =SUM(U19:U23) -> 11249.552
A25: TOTAL ASSETS | B25: =B16+B24 -> 107913.36 | C25: =C16+C24 -> 99789.034 | D25: =D16+D24 -> 104599.67 | E25: =E16+E24 -> 134890.21 | F25: =F16+F24 -> 134890.21 | G25: =G16+G24 -> 120192.4 | H25: =H16+H24 -> 111459.69 | I25: =I16+I24 -> 117608.98 | ... U25: =U16+U24 -> 142329.26
A27: LIABILITIES & STOCKHOLDERS' EQUITY
A28: Current Liabilities
A29: Accounts payable | B29: ='Income Statement'!B10/91*7 -> 1323.0698 | C29: ='Income Statement'!C10/91*7 -> 1140.0708 | D29: ='Income Statement'!D10/91*7 -> 1254.6395 | E29: 880.59 | F29: =E29 -> 880.59 | G29: 1275.061 | H29: ='Income Statement'!H10/91*Assumptions!H19 -> 1318.1365 | I29: ='Income Statement'!I10/91*Assumptions!I19 -> 1393.2425 | J29: ='Income Statement'!J10/91*Assumptions!J19 -> 1406.4657 | K29: =J29 -> 1406.4657 | L29: ='Income Statement'!L10/91*Assumptions!L19 -> 1639.6042 | M29: ='Income Statement'!M10/91*Assumptions!M19 -> 1423.5875 | N29: ='Income Statement'!N10/91*Assumptions!N19 -> 1510.5491 | O29: ='Income Statement'!O10/91*Assumptions!O19 -> 1528.8464 | P29: =O29 -> 1528.8464 | Q29: ='Income Statement'!Q10/91*Assumptions!Q19 -> 1770.7725 | R29: ='Income Statement'!R10/91*Assumptions!R19 -> 1537.4745 | S29: ='Income Statement'!S10/91*Assumptions!S19 -> 1631.3931 | T29: ='Income Statement'!T10/91*Assumptions!T19 -> 1651.1541 | U29: =T29 -> 1651.1541 | W29: ACTUALS: $880,590 (12/31/2025), $1,275,061 (3/31/2026). Driver = Cost of Services/91 x DPO (Assumptions row 19, ~7 days).
A30: Accrued expenses | B30: =$E$30 -> 3326.445 | C30: =$E$30 -> 3326.445 | D30: =$E$30 -> 3326.445 | E30: 3326.445 | F30: =E30 -> 3326.445 | G30: 4052.64 | H30: ='Income Statement'!H6/'Income Statement'!$G$6*$G$30 -> 3518.7074 | I30: ='Income Statement'!I6/'Income Statement'!$G$6*$G$30 -> 3733.6522 | J30: ='Income Statement'!J6/'Income Statement'!$G$6*$G$30 -> 3778.878 | K30: =J30 -> 3778.878 | L30: ='Income Statement'!L6/'Income Statement'!$G$6*$G$30 -> 4376.8512 | M30: ='Income Statement'!M6/'Income Statement'!$G$6*$G$30 -> 3800.204 | N30: ='Income Statement'!N6/'Income Statement'!$G$6*$G$30 -> 4032.3444 | O30: ='Income Statement'!O6/'Income Statement'!$G$6*$G$30 -> 4081.1882 | P30: =O30 -> 4081.1882 | Q30: ='Income Statement'!Q6/'Income Statement'!$G$6*$G$30 -> 4726.9993 | R30: ='Income Statement'!R6/'Income Statement'!$G$6*$G$30 -> 4104.2203 | S30: ='Income Statement'!S6/'Income Statement'!$G$6*$G$30 -> 4354.932 | T30: ='Income Statement'!T6/'Income Statement'!$G$6*$G$30 -> 4407.6833 | U30: =T30 -> 4407.6833 | W30: ACTUALS: $3,326,445 (12/31/2025), $4,052,640 (3/31/2026). 2026Q2-2028 scaled with revenue relative to 2026Q1.
A31: Operating lease liabilities, current | B31: =$E$31 -> 639.805 | C31: =$E$31 -> 639.805 | D31: =$E$31 -> 639.805 | E31: 639.805 | F31: =E31 -> 639.805 | G31: 756.708 | H31: =G31*0.99 -> 749.14092 | I31: =H31*0.99 -> 741.64951 | J31: =I31*0.99 -> 734.23302 | K31: =J31 -> 734.23302 | L31: =K31*0.99 -> 726.89069 | M31: =L31*0.99 -> 719.62178 | N31: =M31*0.99 -> 712.42556 | O31: =N31*0.99 -> 705.30131 | P31: =O31 -> 705.30131 | Q31: =P31*0.99 -> 698.24829 | R31: =Q31*0.99 -> 691.26581 | S31: =R31*0.99 -> 684.35315 | T31: =S31*0.99 -> 677.50962 | U31: =T31 -> 677.50962 | W31: ACTUALS: $639,805 (12/31/2025), $756,708 (3/31/2026). 2026Q2-2028: held roughly flat (-1%/qtr).
A32: Equipment loan, current portion | B32: =$E$32 -> 289.317 | C32: =$E$32 -> 289.317 | D32: =$E$32 -> 289.317 | E32: 289.317 | F32: =E32 -> 289.317 | G32: 337.544 | H32: =G32 -> 337.544 | I32: =H32 -> 337.544 | J32: =I32 -> 337.544 | K32: =J32 -> 337.544 | L32: =K32 -> 337.544 | M32: =L32 -> 337.544 | N32: =M32 -> 337.544 | O32: =N32 -> 337.544 | ... U32: =T32 -> 337.544 | W32: ACTUALS: $289,317 (12/31/2025), $337,544 (3/31/2026). Held flat going forward.
A33: Settlement processing obligations | B33: =B10 -> 61625.34 | C33: =C10 -> 55890.772 | D33: =D10 -> 59304.932 | E33: =E10 -> 74180.475 | F33: =F10 -> 74180.475 | G33: =G10 -> 69522.444 | H33: =H10 -> 61909.896 | I33: =I10 -> 65691.743 | ... U33: =U10 -> 77550.982 | W33: Exactly equals Settlement processing assets (row 10) per 10-Q — a 1:1 pass-through liability.
A34: Prepaid card load obligations | B34: =B11 -> 14305.882 | C34: =C11 -> 12974.644 | D34: =D11 -> 13767.216 | E34: =E11 -> 27623.728 | F34: =F11 -> 27623.728 | G34: =G11 -> 15466.828 | H34: =H11 -> 14371.94 | I34: =I11 -> 15249.869 | ... U34: =U11 -> 18002.906 | W34: Exactly equals Prepaid card load assets (row 11) per 10-Q — a 1:1 pass-through liability.
A35: Customer deposits (liability) | B35: =B12 -> 2200.905 | C35: =C12 -> 1996.099 | D35: =D12 -> 2118.0333 | E35: =E12 -> 2281.22 | F35: =F12 -> 2281.22 | G35: =G12 -> 2239.829 | H35: =H12 -> 2211.0677 | I35: =I12 -> 2346.1337 | ... U35: =U12 -> 2769.6779 | W35: Exactly equals Customer deposits (asset, row 12) per 10-Q — a 1:1 pass-through liability.
A36: Merchant reserve obligations | B36: =B14 -> 4401.81 | C36: =C14 -> 3992.198 | D36: =D14 -> 4236.0666 | E36: =E14 -> 4795.537 | F36: =F14 -> 4795.537 | G36: =G14 -> 4617.537 | H36: =H14 -> 4422.1355 | I36: =I14 -> 4692.2673 | ... U36: =U14 -> 5539.3558 | W36: Exactly equals Merchant reserves (asset, row 14) per 10-Q — a 1:1 pass-through liability.
A37: Total Current Liabilities | B37: =SUM(B29:B36) -> 88112.574 | C37: =SUM(C29:C36) -> 80249.35 | D37: =SUM(D29:D36) -> 84936.455 | E37: =SUM(E29:E36) -> 114017.12 | F37: =SUM(F29:F36) -> 114017.12 | G37: =SUM(G29:G36) -> 98268.591 | H37: =SUM(H29:H36) -> 88838.569 | I37: =SUM(I29:I36) -> 94186.101 | ... U37: =SUM(U29:U36) -> 110936.81
A39: Non-Current Liabilities
A40: Equipment loan, non-current | B40: =$E$40 -> 1074.711 | C40: =$E$40 -> 1074.711 | D40: =$E$40 -> 1074.711 | E40: 1074.711 | F40: =E40 -> 1074.711 | G40: 987.996 | H40: =G40*0.95 -> 938.5962 | I40: =H40*0.95 -> 891.66639 | J40: =I40*0.95 -> 847.08307 | K40: =J40 -> 847.08307 | L40: =K40*0.95 -> 804.72892 | M40: =L40*0.95 -> 764.49247 | N40: =M40*0.95 -> 726.26785 | O40: =N40*0.95 -> 689.95446 | P40: =O40 -> 689.95446 | Q40: =P40*0.95 -> 655.45673 | R40: =Q40*0.95 -> 622.6839 | S40: =R40*0.95 -> 591.5497 | T40: =S40*0.95 -> 561.97222 | U40: =T40 -> 561.97222 | W40: ACTUALS: $1,074,711 (12/31/2025), $987,996 (3/31/2026). 2026Q2-2028: amortizing ~5%/qtr.
A41: Operating lease liabilities, non-current | B41: =$E$41 -> 1885.983 | C41: =$E$41 -> 1885.983 | D41: =$E$41 -> 1885.983 | E41: 1885.983 | F41: =E41 -> 1885.983 | G41: 2790.905 | H41: =G41*0.98 -> 2735.0869 | I41: =H41*0.98 -> 2680.3852 | J41: =I41*0.98 -> 2626.7775 | K41: =J41 -> 2626.7775 | L41: =K41*0.98 -> 2574.2419 | M41: =L41*0.98 -> 2522.7571 | N41: =M41*0.98 -> 2472.3019 | O41: =N41*0.98 -> 2422.8559 | P41: =O41 -> 2422.8559 | Q41: =P41*0.98 -> 2374.3988 | R41: =Q41*0.98 -> 2326.9108 | S41: =R41*0.98 -> 2280.3726 | T41: =S41*0.98 -> 2234.7651 | U41: =T41 -> 2234.7651 | W41: ACTUALS: $1,885,983 (12/31/2025), $2,790,905 (3/31/2026) — increase reflects new lease per 10-Q. 2026Q2-2028: amortizing ~2%/qtr.
A42: Total Non-Current Liabilities | B42: =SUM(B40:B41) -> 2960.694 | C42: =SUM(C40:C41) -> 2960.694 | D42: =SUM(D40:D41) -> 2960.694 | E42: =SUM(E40:E41) -> 2960.694 | F42: =SUM(F40:F41) -> 2960.694 | G42: =SUM(G40:G41) -> 3778.901 | H42: =SUM(H40:H41) -> 3673.6831 | I42: =SUM(I40:I41) -> 3572.0516 | ... U42: =SUM(U40:U41) -> 2796.7373
A43: TOTAL LIABILITIES | B43: =B37+B42 -> 91073.268 | C43: =C37+C42 -> 83210.044 | D43: =D37+D42 -> 87897.149 | E43: =E37+E42 -> 116977.81 | F43: =F37+F42 -> 116977.81 | G43: =G37+G42 -> 102047.49 | H43: =H37+H42 -> 92512.252 | I43: =I37+I42 -> 97758.153 | ... U43: =U37+U42 -> 113733.55
A45: Stockholders' Equity
A46: Common stock + APIC, net of treasury & deferred comp | B46: =$E$46 -> 88457.398 | C46: =$E$46 -> 88457.398 | D46: =$E$46 -> 88457.398 | E46: 88457.398 | F46: =E46 -> 88457.398 | G46: 88567.403 | H46: =G46+'Income Statement'!H13-Assumptions!H25+'Cash Flow Statement'!H26 -> 88716.842 | I46: =H46+'Income Statement'!I13-Assumptions!I25+'Cash Flow Statement'!I26 -> 88883.839 | J46: =I46+'Income Statement'!J13-Assumptions!J25+'Cash Flow Statement'!J26 -> 89054.531 | K46: =J46 -> 89054.531 | L46: =K46+'Income Statement'!L13-Assumptions!L25+'Cash Flow Statement'!L26 -> 89274.07 | M46: =L46+'Income Statement'!M13-Assumptions!M25+'Cash Flow Statement'!M26 -> 89446.504 | N46: =M46+'Income Statement'!N13-Assumptions!N25+'Cash Flow Statement'!N26 -> 89637.902 | O46: =N46+'Income Statement'!O13-Assumptions!O25+'Cash Flow Statement'!O26 -> 89833.289 | P46: =O46 -> 89833.289 | Q46: =P46+'Income Statement'!Q13-Assumptions!Q25+'Cash Flow Statement'!Q26 -> 90081.431 | R46: =Q46+'Income Statement'!R13-Assumptions!R25+'Cash Flow Statement'!R26 -> 90278.7 | S46: =R46+'Income Statement'!S13-Assumptions!S25+'Cash Flow Statement'!S26 -> 90496.449 | T46: =S46+'Income Statement'!T13-Assumptions!T25+'Cash Flow Statement'!T26 -> 90718.507 | U46: =T46 -> 90718.507 | W46: ACTUALS computed from Q1 2026 10-Q components: 12/31/2025 = common stock $31,562 + APIC $102,363,590 - treasury stock $6,837,181 - deferred compensation $7,100,573 = $88,457,398. 3/31/2026 = $31,667+$102,455,703-$7,070,640-$6,849,327 = $88,567,403. 2026Q2-2028: prior + Stock-based compensation expense (Income Statement row 13) - share repurchases (Assumptions row 25).
A47: Accumulated deficit | B47: =C47-'Income Statement'!C24 -> -68278.345 | C47: =D47-'Income Statement'!D24 -> -68644.995 | D47: =$E$47-'Income Statement'!E24 -> -69044.995 | E47: -70544.995 | F47: =E47 -> -70544.995 | G47: -70422.492 | H47: =G47+'Income Statement'!H24 -> -69769.403 | I47: =H47+'Income Statement'!I24 -> -69033.008 | J47: =I47+'Income Statement'!J24 -> -68255.612 | K47: =J47 -> -68255.612 | L47: =K47+'Income Statement'!L24 -> -67466.635 | M47: =L47+'Income Statement'!M24 -> -66768.971 | N47: =M47+'Income Statement'!N24 -> -66034.547 | O47: =N47+'Income Statement'!O24 -> -65292.389 | P47: =O47 -> -65292.389 | Q47: =P47+'Income Statement'!Q24 -> -64447.967 | R47: =Q47+'Income Statement'!R24 -> -63702.161 | S47: =R47+'Income Statement'!S24 -> -62916.656 | T47: =S47+'Income Statement'!T24 -> -62122.797 | U47: =T47 -> -62122.797 | W47: ACTUALS: $(70,544,995) at 12/31/2025 and $(70,422,492) at 3/31/2026, per Q1 2026 10-Q (the $122,503 improvement = 2026Q1 net income, ties exactly: -70,544.995+122.503=-70,422.492 ✓). 2025 Q1-Q3 backed out from the 12/31/2025 actual using each quarter's modeled net income (Income Statement row 24). 2026Q2-2028: prior balance + Net Income.
A48: TOTAL STOCKHOLDERS' EQUITY | B48: =B46+B47 -> 20179.053 | C48: =C46+C47 -> 19812.403 | D48: =D46+D47 -> 19412.403 | E48: =E46+E47 -> 17912.403 | F48: =F46+F47 -> 17912.403 | G48: =G46+G47 -> 18144.911 | H48: =H46+H47 -> 18947.439 | I48: =I46+I47 -> 19850.831 | ... U48: =U46+U47 -> 28595.71
A49: TOTAL LIABILITIES & EQUITY | B49: =B43+B48 -> 111252.32 | C49: =C43+C48 -> 103022.45 | D49: =D43+D48 -> 107309.55 | E49: =E43+E48 -> 134890.21 | F49: =F43+F48 -> 134890.21 | G49: =G43+G48 -> 120192.4 | H49: =H43+H48 -> 111459.69 | I49: =I43+I48 -> 117608.98 | ... U49: =U43+U48 -> 142329.26
A51: Balance check (Assets - L&E, should = 0) | B51: =B25-B49 -> -3338.9579 | C51: =C25-C49 -> -3233.4131 | D51: =D25-D49 -> -2709.881 | E51: =E25-E49 -> 0 | F51: =F25-F49 -> 0 | G51: =G25-G49 -> 0 | H51: =H25-H49 -> 0 | I51: =I25-I49 -> 0 | ... U51: =U25-U49 -> 0

Sheet Cash Flow Statement
A1: Usio, Inc. — Consolidated Statement of Cash Flows (Quarterly)
A2: ($ in thousands)
A4: Fiscal Period | B4: 2025Q1A | C4: 2025Q2A | D4: 2025Q3A | E4: 2025Q4A | F4: FY2025A | G4: 2026Q1A | H4: 2026Q2E | I4: 2026Q3E | J4: 2026Q4E | K4: FY2026E | L4: 2027Q1E | M4: 2027Q2E | N4: 2027Q3E | O4: 2027Q4E | P4: FY2027E | Q4: 2028Q1E | R4: 2028Q2E | S4: 2028Q3E | T4: 2028Q4E | U4: FY2028E
A6: Cash Flows from Operating Activities
A7: Net income (loss) | B7: ='Income Statement'!B24 -> -234.97 | C7: ='Income Statement'!C24 -> -366.65 | D7: ='Income Statement'!D24 -> -400 | E7: ='Income Statement'!E24 -> -1500 | F7: =SUM(B7:E7) -> -2501.62 | G7: ='Income Statement'!G24 -> 191.168 | H7: ='Income Statement'!H24 -> 653.08907 | I7: ='Income Statement'!I24 -> 736.39449 | J7: ='Income Statement'!J24 -> 777.39654 | K7: =SUM(G7:J7) -> 2358.0481 | L7: ='Income Statement'!L24 -> 788.97656 | M7: ='Income Statement'!M24 -> 697.66419 | N7: ='Income Statement'!N24 -> 734.42374 | O7: ='Income Statement'!O24 -> 742.15818 | P7: =SUM(L7:O7) -> 2963.2227 | Q7: ='Income Statement'!Q24 -> 844.42268 | R7: ='Income Statement'!R24 -> 745.80533 | S7: ='Income Statement'!S24 -> 785.50564 | T7: ='Income Statement'!T24 -> 793.85883 | U7: =SUM(Q7:T7) -> 3169.5925
A8: Add back: Depreciation & amortization | B8: ='Income Statement'!B15 -> 495.77 | C8: ='Income Statement'!C15 -> 464.599 | D8: ='Income Statement'!D15 -> 432.846 | E8: ='Income Statement'!E15 -> 353.518 | F8: =SUM(B8:E8) -> 1746.733 | G8: ='Income Statement'!G15 -> 225.745 | H8: ='Income Statement'!H15 -> 243.21745 | I8: ='Income Statement'!I15 -> 258.0747 | J8: ='Income Statement'!J15 -> 261.20076 | K8: =SUM(G8:J8) -> 988.23792 | L8: ='Income Statement'!L15 -> 302.53342 | M8: ='Income Statement'!M15 -> 262.67485 | N8: ='Income Statement'!N15 -> 278.72068 | O8: ='Income Statement'!O15 -> 282.09682 | P8: =SUM(L8:O8) -> 1126.0258 | Q8: ='Income Statement'!Q15 -> 326.73609 | R8: ='Income Statement'!R15 -> 283.68883 | S8: ='Income Statement'!S15 -> 301.01833 | T8: ='Income Statement'!T15 -> 304.66457 | U8: =SUM(Q8:T8) -> 1216.1078
A9: Add back: Stock-based compensation | B9: ='Income Statement'!B13 -> 410.062 | C9: ='Income Statement'!C13 -> 434.255 | D9: ='Income Statement'!D13 -> 399.582 | E9: ='Income Statement'!E13 -> 315.63 | F9: =SUM(B9:E9) -> 1559.529 | G9: ='Income Statement'!G13 -> 329.284 | H9: ='Income Statement'!H13 -> 287.4388 | I9: ='Income Statement'!I13 -> 304.99738 | J9: ='Income Statement'!J13 -> 308.69181 | K9: =SUM(G9:J9) -> 1230.412 | L9: ='Income Statement'!L13 -> 357.5395 | M9: ='Income Statement'!M13 -> 310.43391 | N9: ='Income Statement'!N13 -> 329.39717 | O9: ='Income Statement'!O13 -> 333.38716 | P9: =SUM(L9:O9) -> 1330.7577 | Q9: ='Income Statement'!Q13 -> 386.14265 | R9: ='Income Statement'!R13 -> 335.26862 | S9: ='Income Statement'!S13 -> 355.74894 | T9: ='Income Statement'!T13 -> 360.05813 | U9: =SUM(Q9:T9) -> 1437.2183
A10: Changes in working capital:
A11: (Increase)/decrease in accounts receivable | B11: 0 | C11: ='Balance Sheet'!B9-'Balance Sheet'!C9 -> 427.61692 | D11: ='Balance Sheet'!C9-'Balance Sheet'!D9 -> -254.5881 | E11: ='Balance Sheet'!D9-'Balance Sheet'!E9 -> -852.31867 | F11: =SUM(B11:E11) -> -679.28985 | G11: ='Balance Sheet'!F9-'Balance Sheet'!G9 -> -144.067 | H11: ='Balance Sheet'!G9-'Balance Sheet'!H9 -> 802.13796 | I11: ='Balance Sheet'!H9-'Balance Sheet'!I9 -> -282.00582 | J11: ='Balance Sheet'!I9-'Balance Sheet'!J9 -> -59.335794 | K11: =SUM(G11:J11) -> 316.72935 | L11: ='Balance Sheet'!K9-'Balance Sheet'!L9 -> -784.53591 | M11: ='Balance Sheet'!L9-'Balance Sheet'!M9 -> 756.55632 | N11: ='Balance Sheet'!M9-'Balance Sheet'!N9 -> -304.56628 | O11: ='Balance Sheet'!N9-'Balance Sheet'!O9 -> -64.082658 | P11: =SUM(L11:O11) -> -396.62853 | Q11: ='Balance Sheet'!P9-'Balance Sheet'!Q9 -> -847.29879 | R11: ='Balance Sheet'!Q9-'Balance Sheet'!R9 -> 817.08083 | S11: ='Balance Sheet'!R9-'Balance Sheet'!S9 -> -328.93159 | T11: ='Balance Sheet'!S9-'Balance Sheet'!T9 -> -69.209271 | U11: =SUM(Q11:T11) -> -428.35881 | W11: 2025Q1 set to 0 (no FY2024Q4 balance sheet available as starting point). All other quarters = prior quarter AR minus current quarter AR.
A12: Increase/(decrease) in accounts payable | B12: 0 | C12: ='Balance Sheet'!C29-'Balance Sheet'!B29 -> -182.99892 | D12: ='Balance Sheet'!D29-'Balance Sheet'!C29 -> 114.56869 | E12: ='Balance Sheet'!E29-'Balance Sheet'!D29 -> -374.04954 | F12: =SUM(B12:E12) -> -442.47977 | G12: ='Balance Sheet'!G29-'Balance Sheet'!F29 -> 394.471 | H12: ='Balance Sheet'!H29-'Balance Sheet'!G29 -> 43.075531 | I12: ='Balance Sheet'!I29-'Balance Sheet'!H29 -> 75.105927 | J12: ='Balance Sheet'!J29-'Balance Sheet'!I29 -> 13.223192 | K12: =SUM(G12:J12) -> 525.87565 | L12: ='Balance Sheet'!L29-'Balance Sheet'!K29 -> 233.13854 | M12: ='Balance Sheet'!M29-'Balance Sheet'!L29 -> -216.01674 | N12: ='Balance Sheet'!N29-'Balance Sheet'!M29 -> 86.961689 | O12: ='Balance Sheet'!O29-'Balance Sheet'!N29 -> 18.297285 | P12: =SUM(L12:O12) -> 122.38078 | Q12: ='Balance Sheet'!Q29-'Balance Sheet'!P29 -> 241.9261 | R12: ='Balance Sheet'!R29-'Balance Sheet'!Q29 -> -233.29808 | S12: ='Balance Sheet'!S29-'Balance Sheet'!R29 -> 93.918624 | T12: ='Balance Sheet'!T29-'Balance Sheet'!S29 -> 19.761068 | U12: =SUM(Q12:T12) -> 122.30771
A13: Increase/(decrease) in accrued expenses | B13: 0 | C13: ='Balance Sheet'!C30-'Balance Sheet'!B30 -> 0 | D13: ='Balance Sheet'!D30-'Balance Sheet'!C30 -> 0 | E13: ='Balance Sheet'!E30-'Balance Sheet'!D30 -> 0 | F13: =SUM(B13:E13) -> 0 | G13: ='Balance Sheet'!G30-'Balance Sheet'!F30 -> 726.195 | H13: ='Balance Sheet'!H30-'Balance Sheet'!G30 -> -533.93257 | I13: ='Balance Sheet'!I30-'Balance Sheet'!H30 -> 214.94481 | J13: ='Balance Sheet'!J30-'Balance Sheet'!I30 -> 45.225738 | K13: =SUM(G13:J13) -> 452.43298 | L13: ='Balance Sheet'!L30-'Balance Sheet'!K30 -> 597.97322 | M13: ='Balance Sheet'!M30-'Balance Sheet'!L30 -> -576.64717 | N13: ='Balance Sheet'!N30-'Balance Sheet'!M30 -> 232.1404 | O13: ='Balance Sheet'!O30-'Balance Sheet'!N30 -> 48.843797 | P13: =SUM(L13:O13) -> 302.31024 | Q13: ='Balance Sheet'!Q30-'Balance Sheet'!P30 -> 645.81107 | R13: ='Balance Sheet'!R30-'Balance Sheet'!Q30 -> -622.77895 | S13: ='Balance Sheet'!S30-'Balance Sheet'!R30 -> 250.71163 | T13: ='Balance Sheet'!T30-'Balance Sheet'!S30 -> 52.751301 | U13: =SUM(Q13:T13) -> 326.49506
A14: (Increase)/decrease in deferred tax asset | B14: 0 | C14: ='Balance Sheet'!B21-'Balance Sheet'!C21 -> 0 | D14: ='Balance Sheet'!C21-'Balance Sheet'!D21 -> 0 | E14: ='Balance Sheet'!D21-'Balance Sheet'!E21 -> 0 | F14: =SUM(B14:E14) -> 0 | G14: ='Balance Sheet'!F21-'Balance Sheet'!G21 -> 67.084 | H14: ='Balance Sheet'!G21-'Balance Sheet'!H21 -> 279.89531 | I14: ='Balance Sheet'!H21-'Balance Sheet'!I21 -> 315.59764 | J14: ='Balance Sheet'!I21-'Balance Sheet'!J21 -> 333.16994 | K14: =SUM(G14:J14) -> 995.7469 | L14: ='Balance Sheet'!K21-'Balance Sheet'!L21 -> 338.13281 | M14: ='Balance Sheet'!L21-'Balance Sheet'!M21 -> 298.99894 | N14: ='Balance Sheet'!M21-'Balance Sheet'!N21 -> 314.75303 | O14: ='Balance Sheet'!N21-'Balance Sheet'!O21 -> 318.06779 | P14: =SUM(L14:O14) -> 1269.9526 | Q14: ='Balance Sheet'!P21-'Balance Sheet'!Q21 -> 361.89544 | R14: ='Balance Sheet'!Q21-'Balance Sheet'!R21 -> 319.63086 | S14: ='Balance Sheet'!R21-'Balance Sheet'!S21 -> 336.64527 | T14: ='Balance Sheet'!S21-'Balance Sheet'!T21 -> 340.22521 | U14: =SUM(Q14:T14) -> 1358.3968 | W14: Decrease in DTA balance (NOL utilization) = source of cash; reverses the non-cash tax expense already reflected in Net Income.
A15: Change in settlement/prepaid/customer-deposit/reserve balances, net | B15: 0 | C15: =('Balance Sheet'!C33-'Balance Sheet'!B33)+('Balance Sheet'!C34-'Balance Sheet'!B34)+('Balance Sheet'!C35-'Balance Sheet'!B35)+('Balance Sheet'!C36-'Balance Sheet'!B36)-('Balance Sheet'!C10-'Balance Sheet'!B10)-('Balance Sheet'!C11-'Balance Sheet'!B11)-('Balance Sheet'!C12-'Balance Sheet'!B12)-('Balance Sheet'!C14-'Balance Sheet'!B14) -> 0 | D15: =('Balance Sheet'!D33-'Balance Sheet'!C33)+('Balance Sheet'!D34-'Balance Sheet'!C34)+('Balance Sheet'!D35-'Balance Sheet'!C35)+('Balance Sheet'!D36-'Balance Sheet'!C36)-('Balance Sheet'!D10-'Balance Sheet'!C10)-('Balance Sheet'!D11-'Balance Sheet'!C11)-('Balance Sheet'!D12-'Balance Sheet'!C12)-('Balance Sheet'!D14-'Balance Sheet'!C14) -> 0 | E15: =('Balance Sheet'!E33-'Balance Sheet'!D33)+('Balance Sheet'!E34-'Balance Sheet'!D34)+('Balance Sheet'!E35-'Balance Sheet'!D35)+('Balance Sheet'!E36-'Balance Sheet'!D36)-('Balance Sheet'!E10-'Balance Sheet'!D10)-('Balance Sheet'!E11-'Balance Sheet'!D11)-('Balance Sheet'!E12-'Balance Sheet'!D12)-('Balance Sheet'!E14-'Balance Sheet'!D14) -> 0 | F15: =SUM(B15:E15) -> 0 | G15: =('Balance Sheet'!G33-'Balance Sheet'!F33)+('Balance Sheet'!G34-'Balance Sheet'!F34)+('Balance Sheet'!G35-'Balance Sheet'!F35)+('Balance Sheet'!G36-'Balance Sheet'!F36)-('Balance Sheet'!G10-'Balance Sheet'!F10)-('Balance Sheet'!G11-'Balance Sheet'!F11)-('Balance Sheet'!G12-'Balance Sheet'!F12)-('Balance Sheet'!G14-'Balance Sheet'!F14) -> -1.8189894e-12 | H15: =('Balance Sheet'!H33-'Balance Sheet'!G33)+('Balance Sheet'!H34-'Balance Sheet'!G34)+('Balance Sheet'!H35-'Balance Sheet'!G35)+('Balance Sheet'!H36-'Balance Sheet'!G36)-('Balance Sheet'!H10-'Balance Sheet'!G10)-('Balance Sheet'!H11-'Balance Sheet'!G11)-('Balance Sheet'!H12-'Balance Sheet'!G12)-('Balance Sheet'!H14-'Balance Sheet'!G14) -> 0 | I15: =('Balance Sheet'!I33-'Balance Sheet'!H33)+('Balance Sheet'!I34-'Balance Sheet'!H34)+('Balance Sheet'!I35-'Balance Sheet'!H35)+('Balance Sheet'!I36-'Balance Sheet'!H36)-('Balance Sheet'!I10-'Balance Sheet'!H10)-('Balance Sheet'!I11-'Balance Sheet'!H11)-('Balance Sheet'!I12-'Balance Sheet'!H12)-('Balance Sheet'!I14-'Balance Sheet'!H14) -> 0 | J15: =('Balance Sheet'!J33-'Balance Sheet'!I33)+('Balance Sheet'!J34-'Balance Sheet'!I34)+('Balance Sheet'!J35-'Balance Sheet'!I35)+('Balance Sheet'!J36-'Balance Sheet'!I36)-('Balance Sheet'!J10-'Balance Sheet'!I10)-('Balance Sheet'!J11-'Balance Sheet'!I11)-('Balance Sheet'!J12-'Balance Sheet'!I12)-('Balance Sheet'!J14-'Balance Sheet'!I14) -> 0 | K15: =SUM(G15:J15) -> -1.8189894e-12 | L15: =('Balance Sheet'!L33-'Balance Sheet'!K33)+('Balance Sheet'!L34-'Balance Sheet'!K34)+('Balance Sheet'!L35-'Balance Sheet'!K35)+('Balance Sheet'!L36-'Balance Sheet'!K36)-('Balance Sheet'!L10-'Balance Sheet'!K10)-('Balance Sheet'!L11-'Balance Sheet'!K11)-('Balance Sheet'!L12-'Balance Sheet'!K12)-('Balance Sheet'!L14-'Balance Sheet'!K14) -> 0 | M15: =('Balance Sheet'!M33-'Balance Sheet'!L33)+('Balance Sheet'!M34-'Balance Sheet'!L34)+('Balance Sheet'!M35-'Balance Sheet'!L35)+('Balance Sheet'!M36-'Balance Sheet'!L36)-('Balance Sheet'!M10-'Balance Sheet'!L10)-('Balance Sheet'!M11-'Balance Sheet'!L11)-('Balance Sheet'!M12-'Balance Sheet'!L12)-('Balance Sheet'!M14-'Balance Sheet'!L14) -> 0 | N15: =('Balance Sheet'!N33-'Balance Sheet'!M33)+('Balance Sheet'!N34-'Balance Sheet'!M34)+('Balance Sheet'!N35-'Balance Sheet'!M35)+('Balance Sheet'!N36-'Balance Sheet'!M36)-('Balance Sheet'!N10-'Balance Sheet'!M10)-('Balance Sheet'!N11-'Balance Sheet'!M11)-('Balance Sheet'!N12-'Balance Sheet'!M12)-('Balance Sheet'!N14-'Balance Sheet'!M14) -> 0 | O15: =('Balance Sheet'!O33-'Balance Sheet'!N33)+('Balance Sheet'!O34-'Balance Sheet'!N34)+('Balance Sheet'!O35-'Balance Sheet'!N35)+('Balance Sheet'!O36-'Balance Sheet'!N36)-('Balance Sheet'!O10-'Balance Sheet'!N10)-('Balance Sheet'!O11-'Balance Sheet'!N11)-('Balance Sheet'!O12-'Balance Sheet'!N12)-('Balance Sheet'!O14-'Balance Sheet'!N14) -> 0 | P15: =SUM(L15:O15) -> 0 | Q15: =('Balance Sheet'!Q33-'Balance Sheet'!P33)+('Balance Sheet'!Q34-'Balance Sheet'!P34)+('Balance Sheet'!Q35-'Balance Sheet'!P35)+('Balance Sheet'!Q36-'Balance Sheet'!P36)-('Balance Sheet'!Q10-'Balance Sheet'!P10)-('Balance Sheet'!Q11-'Balance Sheet'!P11)-('Balance Sheet'!Q12-'Balance Sheet'!P12)-('Balance Sheet'!Q14-'Balance Sheet'!P14) -> 0 | R15: =('Balance Sheet'!R33-'Balance Sheet'!Q33)+('Balance Sheet'!R34-'Balance Sheet'!Q34)+('Balance Sheet'!R35-'Balance Sheet'!Q35)+('Balance Sheet'!R36-'Balance Sheet'!Q36)-('Balance Sheet'!R10-'Balance Sheet'!Q10)-('Balance Sheet'!R11-'Balance Sheet'!Q11)-('Balance Sheet'!R12-'Balance Sheet'!Q12)-('Balance Sheet'!R14-'Balance Sheet'!Q14) -> 0 | S15: =('Balance Sheet'!S33-'Balance Sheet'!R33)+('Balance Sheet'!S34-'Balance Sheet'!R34)+('Balance Sheet'!S35-'Balance Sheet'!R35)+('Balance Sheet'!S36-'Balance Sheet'!R36)-('Balance Sheet'!S10-'Balance Sheet'!R10)-('Balance Sheet'!S11-'Balance Sheet'!R11)-('Balance Sheet'!S12-'Balance Sheet'!R12)-('Balance Sheet'!S14-'Balance Sheet'!R14) -> 0 | T15: =('Balance Sheet'!T33-'Balance Sheet'!S33)+('Balance Sheet'!T34-'Balance Sheet'!S34)+('Balance Sheet'!T35-'Balance Sheet'!S35)+('Balance Sheet'!T36-'Balance Sheet'!S36)-('Balance Sheet'!T10-'Balance Sheet'!S10)-('Balance Sheet'!T11-'Balance Sheet'!S11)-('Balance Sheet'!T12-'Balance Sheet'!S12)-('Balance Sheet'!T14-'Balance Sheet'!S14) -> 0 | U15: =SUM(Q15:T15) -> 0 | W15: Since settlement/prepaid/customer-deposit/merchant-reserve assets and liabilities move 1:1 (asset=liability, confirmed by 10-Q actuals), the net cash impact of these balances nets to exactly zero in this model — included for completeness and as a placeholder should the asset/liability driver assumptions ever diverge.
A16: Other working capital changes (inventory, prepaid exp., leases), net | B16: 0 | C16: =('Balance Sheet'!B13-'Balance Sheet'!C13)+('Balance Sheet'!B15-'Balance Sheet'!C15) -> 0 | D16: =('Balance Sheet'!C13-'Balance Sheet'!D13)+('Balance Sheet'!C15-'Balance Sheet'!D15) -> 0 | E16: =('Balance Sheet'!D13-'Balance Sheet'!E13)+('Balance Sheet'!D15-'Balance Sheet'!E15) -> 0 | F16: =SUM(B16:E16) -> 0 | G16: =('Balance Sheet'!F13-'Balance Sheet'!G13)+('Balance Sheet'!F15-'Balance Sheet'!G15) -> -475.506 | H16: =('Balance Sheet'!G13-'Balance Sheet'!H13)+('Balance Sheet'!G15-'Balance Sheet'!H15) -> 0 | I16: =('Balance Sheet'!H13-'Balance Sheet'!I13)+('Balance Sheet'!H15-'Balance Sheet'!I15) -> 0 | J16: =('Balance Sheet'!I13-'Balance Sheet'!J13)+('Balance Sheet'!I15-'Balance Sheet'!J15) -> 0 | K16: =SUM(G16:J16) -> -475.506 | L16: =('Balance Sheet'!K13-'Balance Sheet'!L13)+('Balance Sheet'!K15-'Balance Sheet'!L15) -> 0 | M16: =('Balance Sheet'!L13-'Balance Sheet'!M13)+('Balance Sheet'!L15-'Balance Sheet'!M15) -> 0 | N16: =('Balance Sheet'!M13-'Balance Sheet'!N13)+('Balance Sheet'!M15-'Balance Sheet'!N15) -> 0 | O16: =('Balance Sheet'!N13-'Balance Sheet'!O13)+('Balance Sheet'!N15-'Balance Sheet'!O15) -> 0 | P16: =SUM(L16:O16) -> 0 | Q16: =('Balance Sheet'!P13-'Balance Sheet'!Q13)+('Balance Sheet'!P15-'Balance Sheet'!Q15) -> 0 | R16: =('Balance Sheet'!Q13-'Balance Sheet'!R13)+('Balance Sheet'!Q15-'Balance Sheet'!R15) -> 0 | S16: =('Balance Sheet'!R13-'Balance Sheet'!S13)+('Balance Sheet'!R15-'Balance Sheet'!S15) -> 0 | T16: =('Balance Sheet'!S13-'Balance Sheet'!T13)+('Balance Sheet'!S15-'Balance Sheet'!T15) -> 0 | U16: =SUM(Q16:T16) -> 0 | W16: Plug capturing changes in inventory and prepaid expenses/other current assets. Operating lease ROU assets are now constructed to move exactly with operating lease liabilities (Balance Sheet), so those items net to zero in this cash flow reconciliation by design.
A17: Net Cash from Operating Activities | B17: =SUM(B7:B16) -> 670.862 | C17: =SUM(C7:C16) -> 776.822 | D17: =SUM(D7:D16) -> 292.40859 | E17: =SUM(E7:E16) -> -2057.2202 | F17: =SUM(B17:E17) -> -317.12762 | G17: =SUM(G7:G16) -> 1314.374 | H17: =SUM(H7:H16) -> 1774.9216 | I17: =SUM(I7:I16) -> 1623.1091 | J17: =SUM(J7:J16) -> 1679.5722 | K17: =SUM(G17:J17) -> 6391.9769 | L17: =SUM(L7:L16) -> 1833.7581 | M17: =SUM(M7:M16) -> 1533.6643 | N17: =SUM(N7:N16) -> 1671.8304 | O17: =SUM(O7:O16) -> 1678.7684 | P17: =SUM(L17:O17) -> 6718.0212 | Q17: =SUM(Q7:Q16) -> 1959.6353 | R17: =SUM(R7:R16) -> 1645.3974 | S17: =SUM(S7:S16) -> 1794.6169 | T17: =SUM(T7:T16) -> 1802.1098 | U17: =SUM(Q17:T17) -> 7201.7594 | W17: 2026Q1 actual operating cash flow was $946,724 (10-Q) vs management commentary of '$0.9 million' (8-K 5/13/2026). FY2025 operating cash flow was reported as positive but not separately quantified in the retrieved excerpts; the modeled FY2025A figure here reflects the 2025Q1-Q3 working-capital interpolations described on the Balance Sheet tab and should be treated as directional rather than exact for FY2025.
A19: Cash Flows from Investing Activities
A20: Capital expenditures & capitalized software | B20: -313.254 | C20: -313.254 | D20: -313.254 | E20: -313.254 | F20: =SUM(B20:E20) -> -1253.016 | G20: -613.604 | H20: =-'Income Statement'!H6*Assumptions!H24 -> -442.21355 | I20: =-'Income Statement'!I6*Assumptions!I24 -> -469.22673 | J20: =-'Income Statement'!J6*Assumptions!J24 -> -474.91048 | K20: =SUM(G20:J20) -> -1999.9548 | L20: =-'Income Statement'!L6*Assumptions!L24 -> -550.06076 | M20: =-'Income Statement'!M6*Assumptions!M24 -> -477.59063 | N20: =-'Income Statement'!N6*Assumptions!N24 -> -506.76487 | O20: =-'Income Statement'!O6*Assumptions!O24 -> -512.90332 | P20: =SUM(L20:O20) -> -2047.3196 | Q20: =-'Income Statement'!Q6*Assumptions!Q24 -> -594.06562 | R20: =-'Income Statement'!R6*Assumptions!R24 -> -515.79788 | S20: =-'Income Statement'!S6*Assumptions!S24 -> -547.30606 | T20: =-'Income Statement'!T6*Assumptions!T24 -> -553.93558 | U20: =SUM(Q20:T20) -> -2211.1051 | W20: 2025Q1 and 2026Q1 actuals from the Q1 2026 10-Q cash flow statement (purchases of PP&E + capitalized internal-use software): $313,254 (Q1 2025) and $613,604 (Q1 2026, elevated due to the new printer installation per 10-K). 2025 Q2-Q4 held at the Q1 2025 level absent quarterly cash-flow detail. 2026Q2-2028: Revenue x Capex % (Assumptions row 24).
A21: Cash, end of period | B21: =B30+B29 -> 7481.373 | C21: =C30+C29 -> 7657.0808 | D21: =D30+D29 -> 7206.1801 | E21: =E30+E29 -> 4789.192 | F21: =E21 -> 4789.192 | G21: =G30+G29 -> 7877.054 | H21: =H30+H29 -> 8874.1032 | I21: =I30+I29 -> 9843.0558 | J21: =J30+J29 -> 10865.134 | K21: =J21 -> 10865.134 | L21: =L30+L29 -> 11968.477 | M21: =M30+M29 -> 12846.315 | N21: =N30+N29 -> 13835.156 | O21: =O30+O29 -> 14826.707 | P21: =O21 -> 14826.707 | Q21: =Q30+Q29 -> 16019.779 | R21: =R30+R29 -> 16978.606 | S21: =S30+S29 -> 18056.782 | T21: =T30+T29 -> 19137.379 | U21: =T21 -> 19137.379
A23: Cash Flows from Financing Activities
A24: Share repurchases | B24: -351.64 | C24: -300 | D24: -250 | E24: -300.872 | F24: =SUM(B24:E24) -> -1202.512 | G24: -233.459 | H24: =-Assumptions!H25 -> -150 | I24: =-Assumptions!I25 -> -150 | J24: =-Assumptions!J25 -> -150 | K24: =SUM(G24:J24) -> -683.459 | L24: =-Assumptions!L25 -> -150 | M24: =-Assumptions!M25 -> -150 | N24: =-Assumptions!N25 -> -150 | O24: =-Assumptions!O25 -> -150 | P24: =SUM(L24:O24) -> -600 | Q24: =-Assumptions!Q25 -> -150 | R24: =-Assumptions!R25 -> -150 | S24: =-Assumptions!S25 -> -150 | T24: =-Assumptions!T25 -> -150 | U24: =SUM(Q24:T24) -> -600 | W24: 2025Q1 ($351,640) and 2026Q1 ($233,459) are exact actuals from 10-Qs. 2025 Q2-Q4 are estimates summing to FY2025's disclosed total of $1.1M ($351,640+300+250+300,872=$1,202,512 — close to the $1.1M figure cited, difference reflects rounding/timing in press release commentary). 2026Q2-2028: Assumptions row 25 ($150K/qtr).
A25: Equipment loan, net repayments | B25: -36.11 | C25: =('Balance Sheet'!C32-'Balance Sheet'!B32)+('Balance Sheet'!C40-'Balance Sheet'!B40) -> 0 | D25: =('Balance Sheet'!D32-'Balance Sheet'!C32)+('Balance Sheet'!D40-'Balance Sheet'!C40) -> 0 | E25: =('Balance Sheet'!E32-'Balance Sheet'!D32)+('Balance Sheet'!E40-'Balance Sheet'!D40) -> 0 | F25: =SUM(B25:E25) -> -36.11 | G25: =('Balance Sheet'!G32-'Balance Sheet'!F32)+('Balance Sheet'!G40-'Balance Sheet'!F40) -> -38.488 | H25: =('Balance Sheet'!H32-'Balance Sheet'!G32)+('Balance Sheet'!H40-'Balance Sheet'!G40) -> -49.3998 | I25: =('Balance Sheet'!I32-'Balance Sheet'!H32)+('Balance Sheet'!I40-'Balance Sheet'!H40) -> -46.92981 | J25: =('Balance Sheet'!J32-'Balance Sheet'!I32)+('Balance Sheet'!J40-'Balance Sheet'!I40) -> -44.58332 | K25: =SUM(G25:J25) -> -179.40093 | L25: =('Balance Sheet'!L32-'Balance Sheet'!K32)+('Balance Sheet'!L40-'Balance Sheet'!K40) -> -42.354154 | M25: =('Balance Sheet'!M32-'Balance Sheet'!L32)+('Balance Sheet'!M40-'Balance Sheet'!L40) -> -40.236446 | N25: =('Balance Sheet'!N32-'Balance Sheet'!M32)+('Balance Sheet'!N40-'Balance Sheet'!M40) -> -38.224624 | O25: =('Balance Sheet'!O32-'Balance Sheet'!N32)+('Balance Sheet'!O40-'Balance Sheet'!N40) -> -36.313392 | P25: =SUM(L25:O25) -> -157.12862 | Q25: =('Balance Sheet'!Q32-'Balance Sheet'!P32)+('Balance Sheet'!Q40-'Balance Sheet'!P40) -> -34.497723 | R25: =('Balance Sheet'!R32-'Balance Sheet'!Q32)+('Balance Sheet'!R40-'Balance Sheet'!Q40) -> -32.772837 | S25: =('Balance Sheet'!S32-'Balance Sheet'!R32)+('Balance Sheet'!S40-'Balance Sheet'!R40) -> -31.134195 | T25: =('Balance Sheet'!T32-'Balance Sheet'!S32)+('Balance Sheet'!T40-'Balance Sheet'!S40) -> -29.577485 | U25: =SUM(Q25:T25) -> -127.98224 | W25: 2025Q1 actual repayment = $36,110 (Q1 2026 10-Q comparative column). Other quarters = change in total equipment loan balances (Balance Sheet).
A26: Proceeds from stock option exercises | B26: 11.515 | C26: 10 | D26: 10 | E26: 10 | F26: =SUM(B26:E26) -> 41.515 | G26: 14.18 | H26: 12 | I26: 12 | J26: 12 | K26: =SUM(G26:J26) -> 50.18 | L26: 12 | M26: 12 | N26: 12 | O26: 12 | P26: =SUM(L26:O26) -> 48 | Q26: 12 | R26: 12 | S26: 12 | T26: 12 | U26: =SUM(Q26:T26) -> 48 | W26: 2025Q1 ($11,515) and 2026Q1 ($14,180) actual from 10-Qs. Other quarters estimated at ~$10-12K/qtr.
A27: Net Cash from (used in) Financing Activities | B27: =SUM(B24:B26) -> -376.235 | C27: =SUM(C24:C26) -> -290 | D27: =SUM(D24:D26) -> -240 | E27: =SUM(E24:E26) -> -290.872 | F27: =SUM(B27:E27) -> -1197.107 | G27: =SUM(G24:G26) -> -257.767 | H27: =SUM(H24:H26) -> -187.3998 | I27: =SUM(I24:I26) -> -184.92981 | J27: =SUM(J24:J26) -> -182.58332 | K27: =SUM(G27:J27) -> -812.67993 | L27: =SUM(L24:L26) -> -180.35415 | M27: =SUM(M24:M26) -> -178.23645 | N27: =SUM(N24:N26) -> -176.22462 | O27: =SUM(O24:O26) -> -174.31339 | P27: =SUM(L27:O27) -> -709.12862 | Q27: =SUM(Q24:Q26) -> -172.49772 | R27: =SUM(R24:R26) -> -170.77284 | S27: =SUM(S24:S26) -> -169.13419 | T27: =SUM(T24:T26) -> -167.57749 | U27: =SUM(Q27:T27) -> -679.98224
A29: Net Increase (Decrease) in Cash | B29: =B17+B20+B27 -> -18.627 | C29: =C17+C20+C27 -> 173.568 | D29: =D17+D20+D27 -> -260.84541 | E29: =E17+E20+E27 -> -2661.3462 | F29: =SUM(B29:E29) -> -2767.2506 | G29: =G17+G20+G27 -> 443.003 | H29: =H17+H20+H27 -> 1145.3082 | I29: =I17+I20+I27 -> 968.95259 | J29: =J17+J20+J27 -> 1022.0784 | K29: =SUM(G29:J29) -> 3579.3422 | L29: =L17+L20+L27 -> 1103.3432 | M29: =M17+M20+M27 -> 877.83722 | N29: =N17+N20+N27 -> 988.84093 | O29: =O17+O20+O27 -> 991.55167 | P29: =SUM(L29:O29) -> 3961.573 | Q29: =Q17+Q20+Q27 -> 1193.0719 | R29: =R17+R20+R27 -> 958.82672 | S29: =S17+S20+S27 -> 1078.1766 | T29: =T17+T20+T27 -> 1080.5968 | U29: =SUM(Q29:T29) -> 4310.672
A30: Cash, beginning of period | B30: 7500 | C30: ='Balance Sheet'!B8 -> 7483.5127 | D30: ='Balance Sheet'!C8 -> 7467.0255 | E30: ='Balance Sheet'!D8 -> 7450.5382 | F30: =B30 -> 7500 | G30: ='Balance Sheet'!F8 -> 7434.051 | H30: ='Balance Sheet'!G8 -> 7728.795 | I30: ='Balance Sheet'!H8 -> 8874.1032 | J30: ='Balance Sheet'!I8 -> 9843.0558 | K30: =G30 -> 7434.051 | L30: ='Balance Sheet'!K8 -> 10865.134 | M30: ='Balance Sheet'!L8 -> 11968.477 | N30: ='Balance Sheet'!M8 -> 12846.315 | O30: ='Balance Sheet'!N8 -> 13835.156 | P30: =L30 -> 10865.134 | Q30: ='Balance Sheet'!P8 -> 14826.707 | R30: ='Balance Sheet'!Q8 -> 16019.779 | S30: ='Balance Sheet'!R8 -> 16978.606 | T30: ='Balance Sheet'!S8 -> 18056.782 | U30: =Q30 -> 14826.707

Sheet Guidance & Street Recon
A1: Usio, Inc. — Guidance & Street Estimate Reconciliation
A2: All $ in thousands except per-share data
A4: FY2026 Management Guidance Reconciliation
A5: Metric | B5: Value | C5: Source / Note
A6: FY2025A Revenue (actual) | B6: ='Income Statement'!F6 -> 85390.373 | C6: 10-K / 8-K (3/18/2026)
A7: Management guidance: FY2026 revenue growth range | B7: 10% - 12% | C7: 8-K 3/18/2026: 'continues to expect strong 10-12% growth in revenue in 2026'
A8: Guidance midpoint growth % | B8: 0.11 | C8: Midpoint of 10-12% range
A9: Implied FY2026E revenue at guidance midpoint | B9: =B6*(1+B8) -> 94783.314 | C9: FY2025A Revenue x 1.11
A10: Model's FY2026E revenue (this workbook) | B10: ='Income Statement'!K6 -> 94783.314 | C10: Sum of 2026Q1A (actual) + Q2-Q4E (Assumptions tab growth drivers)
A11: Variance: Model vs. Guidance Midpoint | B11: =B10-B9 -> -2.0538399e-05 | C11: Model is calibrated so Q2-Q4'26 growth rates (Assumptions row 8) produce a result that matches the guidance midpoint almost exactly (rounding only).
A12: Model's FY2026E revenue growth % | B12: =B10/B6-1 -> 0.11 | C12: Within the 10%-12% guided range, at the 11.0% midpoint.
A13: Management commentary: continued positive Adjusted EBITDA in 2026 | B13: ='Income Statement'!K32 -> 5128.9049 | C13: Model's FY2026E Adj. EBITDA proxy is positive ($5.1M), consistent with guidance for 'continued positive Adjusted EBITDA' (8-K 3/18/2026).
A15: Street (Wall Street Analyst Consensus) Reconciliation
A16: Metric | B16: Value | C16: Source / Note
A17: Street consensus FY2026 revenue estimate | B17: 93890 | C17: Seeking Alpha Earnings Estimates, pulled as of 3/31/2026 ($93.89M)
A18: Variance: Model vs. Street consensus revenue | B18: =B10-B17 -> 893.31401 | C18: Model (calibrated to guidance midpoint) is roughly $0.9M above the pre-2026Q1-print Street consensus.
A19: Variance % | B19: =B10/B17-1 -> 0.0095144745
A20: Street consensus FY2026 EPS estimate | B20: -0.04 | C20: Seeking Alpha Earnings Estimates, pulled as of 3/31/2026
A21: Model's FY2026E diluted EPS | B21: ='Income Statement'!K28 -> 0.084861529 | C21: Model's FY2026E net income / diluted shares
A22: Variance: Model vs. Street consensus EPS | B22: =B21-B20 -> 0.12486153 | C22: The model projects FY2026E EPS of ~$0.085 (positive), well above the pre-Q1-print Street consensus of $(0.04). This large gap is explained below: the Street consensus predates the actual 2026Q1 print, which delivered a 9% revenue beat and 12% Adj. EBITDA beat, plus a swing to GAAP profitability (net income $0.12M vs. a Street-implied loss for the quarter).
A24: 2026Q1 Actual vs. Consensus (already reported)
A25: Metric | B25: Value | C25: Source / Note
A26: 2026Q1A revenue (actual) | B26: ='Income Statement'!G6 -> 25465.776 | C26: 10-Q: $25,465,774; +15.7% YoY (press release rounds to +16%)
A27: Reported: '2026Q1 revenue beat consensus by 9%' | B27: 0.09 | C27: 8-K 5/13/2026 press release headline
A28: Implied pre-print Street estimate for 2026Q1 revenue | B28: ='Income Statement'!G6/(1+B27) -> 23363.097 | C28: 2026Q1A revenue / (1+9%) -- back-solved
A29: 2026Q1A Adj. EBITDA (model proxy) | B29: ='Income Statement'!G32 -> 780.741 | C29: Company-reported actual was $0.8M, beating consensus by 12% (8-K 5/13/2026).
A30: 2026Q1A net income (actual) | B30: ='Income Statement'!G24 -> 191.168 | C30: 10-Q: $122,503 net income (~$0.00 EPS), vs. consensus of $(0.02) EPS, vs. a net loss of $(0.235M) in 2025Q1.
A32: Why the model is more constructive than pre-print Street consensus
A33: 1. The Street consensus of $93.89M revenue / $(0.04) EPS was pulled on 3/31/2026 -- BEFORE the 2026Q1 print (5/13/2026), which beat that quarter's consensus by 9% on revenue and showed a swing to GAAP profitability.
A34: 2. This model incorporates the actual, reported 2026Q1 results (revenue $25.47M, net income $0.12M) and then calibrates Q2-Q4'26 growth so that FULL-YEAR FY2026E revenue lands at the midpoint of management's reaffirmed 10-12% guidance ($94.78M), which is ~1% above the (now partly stale) Street consensus.
A35: 3. On the bottom line, the model projects FY2026E EPS of ~$0.085 vs. the stale Street consensus of $(0.04). Given 2026Q1 alone delivered a profitable quarter (vs. a Street-implied loss), and management guided to 'continued positive Adjusted EBITDA' for the full year, a full-year EPS estimate near breakeven-to-modestly-positive is consistent with the trajectory disclosed to date -- though this remains the single largest area of estimate risk in the model (driven heavily by the Assumptions-tab tax rate, SG&A leverage, and Other income assumptions for 2026Q2-Q4, none of which have been confirmed by subsequent company disclosures as of this model's last data pull).
A36: 4. RECOMMENDATION: when updated Street estimates become available (post-2026Q1 print), replace the consensus figures in B16/B19 above with the refreshed numbers to keep this reconciliation current.

Sheet Scenario Analysis
A1: Usio, Inc. (USIO) — Bull / IR Guide / Base / Bear Scenario Analysis
A2: Cross-referenced: Q1 2026 earnings call, investment thesis, TX ESA SB2 tranche schedule, Indiana universal expansion (July 2026). Arizona REMOVED — ClassWallet entrenched. Indiana + Ohio added as actionable near-term pipeline.
A5: Metric — Scenario Premise | B5: BULL CASE | C5: IR GUIDE CASE | D5: BASE CASE | E5: BEAR CASE | F5: Source / Rationale
A6: Probability (qualitative) | B6: 30% | C6: 15% | D6: 40% | E6: 15% | F6: Directional only. 40% base = calibrated to guidance. 30% bull = Q1 catalyst density. 15% IR Guide = August 15 call with prudent 50% guidance. 15% bear = execution/delay risks.
A7: Core thesis | B7: Full TX ESA + PayFac 20%+ + printer live + PostCredit | C7: 50% of bull catalysts, guided Aug 15 | D7: 11% guidance midpoint, no voucher 2026 | E7: Program delay + client loss + SGA creep
A9: 1. TEXAS ESA — QUARTERLY TRANCHE MODEL (SB2, July 2026 launch confirmed on Q1 call)
A10: Year 1 $600M scaled; Year 2 $800M. Float yield 4% (100% GM). Take-rate 1.65% stepped (from 1.25% base: +40bps for MCC blocking, on-demand ledgering, audit presentment). CEO confirmed $250M July 1 drop on Q1 call.
A11: Quarter | B11: Avg Float Balance | C11: Float Revenue (4%) | D11: Processing Volume | E11: Fee Revenue (1.65%) | F11: Net GP (85% after variable costs)
A12: Q3 2026 — July 1 drop + Sept spike | B12: $220M | C12: $2,200K | D12: $90M | E12: $1,485K | F12: $3,463K
A13: Q4 2026 — Oct 1 tranche + Vol ramp | B13: $335M | C13: $3,350K | D13: $150M | E13: $2,475K | F13: $5,454K
A14: H2 2026 Total | B14: — | C14: $5,550K | D14: $240M | E14: $3,960K | F14: $8,917K
A15: Q1 2027 | B15: $285M | C15: $2,850K | D15: $150M | E15: $2,475K | F15: $4,954K
A16: Q2 2027 | B16: $105M | C16: $1,050K | D16: $210M | E16: $3,465K | F16: $3,995K
A17: Q3 2027 | B17: $310M | C17: $3,100K | D17: $120M | E17: $1,980K | F17: $4,783K
A18: Q4 2027 | B18: $450M | C18: $4,500K | D18: $200M | E18: $3,300K | F18: $7,305K
A19: FY 2027 Total | B19: — | C19: $11,500K | D19: $680M | E19: $11,220K | F19: $21,037K
A21: 2. STATE ESA EXPANSION PIPELINE — INDIANA & OHIO (Near-term; Arizona removed — ClassWallet entrenched)
A22: Why NOT Arizona | F22: Arizona is $1B/yr via ClassWallet (incumbent, multi-year contract). 100,924 students enrolled June 2026. High switching costs. Realistic only as 2028+ RFP re-bid. REMOVED as too aggressive/speculative for near-term model.
A23: INDIANA — Universal Expansion July 2026 (Priority Near-Term Opportunity)
A24: 2024-25 program size | B24: $497M / 76,067 students | C24: $497M actual | D24: $497M actual | E24: $497M actual | F24: Source: Indiana Dept of Education annual report (Indiana Capital Chronicle, July 2025). $497.2M disbursed in 2024-25. 76,067 students, avg award $6,536. 373 participating private schools. Growth was +8.5% (slowing) but about to surge with universal expansion.
A25: July 2026: ALL income limits removed | B25: Universal → 90-100K+ students / $600-650M | C25: Expanding | D25: Expanding | E25: Risk: slower ramp | F25: Source: Chalkbeat Indiana (April 2025), ISI Indiana (confirmed for 2026-27). Indiana lawmakers removed ALL income requirements starting July 2026 — fully universal like Arizona. "About a quarter of the private school population not yet on choice scholarships" per Notre Dame researcher. Additional budget allocated in FY2026 state budget specifically for this expansion.
A26: Payment model | B26: ACH-heavy (school-to-state, state-to-family) | C26: ACH | D26: ACH | E26: ACH only | F26: Indiana pays schools via direct ACH — NOT prepaid card like Texas. Usio's primary lever is ACH modernization for the expanded universal program, not Filtered Spend card. The universal expansion creates a procurement need for scalable payment infrastructure. RFP expected H2 2026.
A27: Usio opportunity (15% share, H2 2027+) | B27: $97.5M vol → $1,700K/yr revenue | C27: $0 (not awarded) | D27: $0 (not modeled) | E27: $0 | F27: If Usio wins 15% of $650M Indiana disbursements = $97.5M volume → ACH fees at 1.25% = $1,219K + float on ~$13.4M avg balance at 4% = $481K = ~$1,700K/yr. Timing: universal July 2026 → RFP H2 2026 → contract award Q1 2027 → first revenue H2 2027. NOT in 2026 model. Bull 2027 upside option only.
A28: OHIO EdCHOICE — Contract Modernization Opportunity
A29: Program size | B29: ~$390-500M / 60,000+ students | C29: ~$390M est | D29: ~$390M est | E29: ~$390M est | F29: Ohio EdChoice Expansion: 60,000 scholarship cap, max awards $6,166 K-8 / $8,408 9-12. Ohio has more voucher programs than any other state. Multiple programs (EdChoice + Autism + Jon Peterson + Cleveland) combined likely $450-500M annually. "Most popular voucher program" per EdChoice.org.
A30: Usio opportunity (10% share, 2027-28+) | B30: $39M vol → $616K/yr revenue | C30: $0 | D30: $0 (not modeled) | E30: $0 | F30: If Usio wins 10% of Ohio flow = $39M → ACH fees $488K + float $128K = ~$616K/yr. Smaller than Indiana. More realistic as a 2027-2028 win given existing state contractor relationships and no imminent universal expansion trigger (Ohio already has income limits).
A31: Combined IN+OH (H2 2027+): ~$2,316K/yr → ~$0.04 EPS add-on to bull 2027 case | F31: Indiana is the priority: universal expansion July 2026 = immediate procurement need. Texas win = Usio's credential. State expansion pipeline: Florida Step Up ($1.1B), Georgia GOAL, Tennessee, North Carolina — all watching TX/IN. These are 2028+ stories, NOT modeled.
A33: 3. OUTPUT SOLUTIONS / IDP — MARGIN STEP-UP MODEL (New printer June 2026, 4x throughput)
A34: Q1 2026A (actual, 10-Q) | B34: $6,822K / 20.2% GM (actual) | C34: actual | D34: actual | E34: actual | F34: Revenue +19% YoY. Electronic docs +41% YoY. Physical mailings +31% YoY. Confirmed actual from Q1 2026 10-Q.
A35: Q2 2026E — transition quarter | B35: $6,400K / 21.0% GM | C35: $6,200K / 20% | D35: $5,880K / 22% | E35: $5,500K / 18% | F35: Temp compression: new printer integration + elevated paper supply. THESIS guidance: keep 20-22% GM in Q2. Bear: printer delayed into Q3, margin stays compressed.
A36: Q3 2026E — printer fully online July | B36: $7,100K / 24.5% GM | C36: $6,800K / 23% | D36: $6,300K / 22.5% | E36: $6,000K / 20% | F36: New printer (4x faster) operational July. Electronic docs >35% YoY. 6 new cities + 2 county govts + 4 enterprise accounts contributing. Zero headcount addition.
A37: Q4 2026E — seasonal municipal peak | B37: $7,600K / 26.0% GM | C37: $7,200K / 24% | D37: $6,400K / 23% | E37: $6,100K / 20% | F37: Annual property tax notices, utility billing cycles, year-end municipal statements. Electronic docs approaching 50% of mix.
A38: FY 2026E | B38: $26,922K / 23.5% = $6,321K GP | C38: $26,022K / 22.5% | D38: $25,402K / 22% | E38: $23,400K / 19.5% | F38: Thesis target: $26.9M / 23.5% blended GM = $6,321.5K GP. Base model: $25.4M / 22%.
A39: FY 2027E | B39: $32,200K / 28.0% = $9,016K GP | C39: $30,000K / 26% | D39: $27,800K / 23% | E39: $24,000K / 20% | F39: Thesis target. 150+ municipal relationships at only 15-25% wallet penetration = massive zero-CAC expansion. TIMING issue (ERP integration, legal mandates, consumer opt-in), NOT a sales issue. 150-300bps annual GM step-up is predictable.
A41: 4. POSTCREDIT — STRUCTURAL LOCK-IN ENGINE (Acquired Nov 2025; all new clients auto-provisioned)
A42: Status | B42: Market-ready H2 2026; all new clients auto-provisioned | C42: Same structure | D42: Not in model | E42: Delayed to 2027 | F42: Q1 2026 call: "rapidly progressing, market-ready launch upcoming." Every new Card/ACH/Prepaid client auto-provisioned PostCredit account at onboarding. G2 confirms customers choose Usio to "eliminate the chaos of managing multiple vendors" — PostCredit deepens this moat.
A43: Revenue (Year 1 bull) | B43: $1,500-2,500K SaaS + float | C43: $500-1,000K | D43: $0 | E43: $0 | F43: Three streams: SaaS subscription per account + float on operational balances (100% GM) + cross-sell velocity. Only in bull model. NOT in base/bear.
A44: Strategic impact | B44: Switching cost flywheel + LTV multiplier | C44: Same structure | D44: Not quantified | E44: Integration friction risk | F44: Every PostCredit client = permanently cross-sold into full Usio suite. LTV increases, churn decreases. Thesis: "transforms Usio from generic payment processor into sticky enterprise software provider."
A46: 5. INTEGRATED P&L SUMMARY ($000)
A47: Metric — FY2026E | B47: BULL CASE | C47: IR GUIDE CASE | D47: BASE CASE | E47: BEAR CASE | F47: Source / Rationale
A48: Revenue
A49: Core business revenue | B49: 94783 | C49: 94783 | D49: 94783 | E49: 90725 | F49: All scenarios share the base segment model calibrated to 11% guidance midpoint (base/bull/guide) or bear client-loss scenario.
A50: Texas ESA H2 2026 (Q3+Q4) | B50: 9510 | C50: 4755 | D50: 0 | E50: 0 | F50: BULL: $3,685K Q3 + $5,825K Q4 = $9,510K per thesis tranche model. IR GUIDE: 50% prudent. BASE/BEAR: zero.
A51: Output Solutions step-up vs base | B51: 1520 | C51: 800 | D51: 0 | E51: 0 | F51: BULL: printer live; Q3 $7.1M + Q4 $7.6M vs base $6.3M/$6.4M = +$1,520K. IR GUIDE: 50%.
A52: PostCredit + other incremental | B52: 2000 | C52: 0 | D52: 0 | E52: 0 | F52: BULL only: early PostCredit onboarding fees + float. Conservative. Not in other scenarios.
A53: TOTAL REVENUE FY2026E | B53: 107813 | C53: 100338 | D53: 94783 | E53: 90725
A57: Revenue growth YoY | B57: 0.263 | C57: 0.175 | D57: 0.11 | E57: 0.063 | F57: BULL +26.3%. IR Guide +17.5%. BASE exactly +11.0% (guidance midpoint). BEAR +6.3% (below 10% guidance floor).
A58: Gross Profit → Operating Leverage → Net Income
A59: Total Gross Profit | B59: 32727 | C59: 25847 | D59: 20928 | E59: 18897 | F59: BULL: core GP $21,160K + TX ESA GP $8,917K + Output delta $850K + PostCredit GP $1,800K. Base: core model. Bear: lower revenue + worse margin mix.
A60: Total SG&A (flat overhead target) | B60: 18900 | C60: 18900 | D60: 18900 | E60: 20400 | F60: Management: "not expected to materially increase this year" — $4.4M/qtr = $17.6M/yr. BEAR: +$1,500K simultaneous implementation hiring. THE key operating leverage metric.
A61: OPERATING INCOME (EBIT) | B61: 13827 | C61: 6947 | D61: 2028 | E61: -1503
A62: NET INCOME (after 30% tax) | B62: 10061 | C62: 5246 | D62: 1801 | E62: -955
A63: DILUTED EPS FY2026E (27.5M shares) | B63: 0.36585455 | C63: 0.19076364 | D63: 0.065490909 | E63: -0.034727273
A64: Thesis anchors: Bull $0.14 / IR $0.07 / Base $0.085 / Bear -$0.03 | B64: 0.14 | C64: 0.07 | D64: 0.0849 | E64: -0.034 | F64: Thesis $0.14 bull = catalyst-layer-only calc. Our integrated model produces higher EPS because it includes full revenue base. Use thesis $0.14 as institutional communication anchor.
A65: Adj. EBITDA FY2026E | B65: 15027 | C65: 8147 | D65: 4228 | E65: 1697 | F65: EBIT + D&A ~$900K + SBC ~$1,300K. All scenarios except BEAR positive — consistent with management guidance for "continued positive Adj. EBITDA."
A67: Metric — FY2027E | B67: BULL CASE | C67: IR GUIDE CASE | D67: BASE CASE | E67: BEAR CASE | F67: Source / Rationale
A68: Core organic revenue | B68: 103213 | C68: 103213 | D68: 103213 | E68: 98244 | F68: 2027 base from model (~8%/qtr growth). Bear uses lower 2026 starting point.
A69: Texas ESA full-year (Section 1) | B69: 22720 | C69: 11360 | D69: 0 | E69: 7904 | F69: BULL: $22,720K per thesis. IR GUIDE: 50%. BASE: not modeled (timing risk). BEAR: 30% drag scenario per thesis stress test ($7,904K).
A70: Indiana + Ohio (H2 2027 if both won) | B70: 2316 | C70: 0 | D70: 0 | E70: 0 | F70: BULL only: Indiana 15% + Ohio 10% = $2,316K/yr first revenue in H2 2027. Contingent on RFP wins H1 2027. ~$0.04 EPS add-on. NOT in IR Guide/Base/Bear.
A71: Output Solutions (thesis scale) | B71: 32200 | C71: 30000 | D71: 27800 | E71: 24000 | F71: BULL: $32.2M / 28% GM (thesis). BASE: $27.8M / 23%. BEAR: $24M / 20%. 15-25% wallet penetration in 150+ existing relationships = runway without new logos.
A72: TOTAL REVENUE FY2027E | B72: 160449 | C72: 144573 | D72: 131013 | E72: 130148
A73: NET INCOME FY2027E | B73: 22479 | C73: 12967 | D73: 7134 | E73: 4062
A74: DILUTED EPS FY2027E | B74: 0.81741818 | C74: 0.47152727 | D74: 0.25941818 | E74: 0.14770909
A75: Thesis anchors: Bull $0.42 / IR $0.21 / Bear $0.05 (Street $0.08) | B75: 0.42 | C75: 0.21 | E75: 0.05 | F75: Thesis: Bull $0.42 at 15x = $6.30 price target. IR Guide $0.21 = 162% above Street $0.08. Bear $0.05 = proves Street already prices in worst case. Risk/reward 3.8:1 ($6.30 bull / $0.75 bear floor).
A77: 6. VALUATION — MULTIPLES & PRICE TARGETS
A78: Metric — Valuation | B78: BULL CASE | C78: IR GUIDE CASE | D78: BASE CASE | E78: BEAR CASE | F78: Source / Rationale
A79: Share price (thesis date) | B79: $1.71 | C79: $1.71 | D79: $1.71 | E79: $1.71 | F79: Thesis date June 11, 2026. 52-wk range $1.03-$2.02. Market cap $47.19M per thesis.
A80: Enterprise Value ($000) | B80: $40,650K | C80: $40,650K | D80: $40,650K | E80: $40,650K | F80: EV = Market cap ($47,025K) - net cash ($6,375K = $7.7M cash - $1.325M equipment loan).
A81: FY2027 forward P/E at $1.71 | B81: 2.1x | C81: 3.6x | D81: 6.6x | E81: 11.4x | F81: Thesis $0.42 = 4.1x. Our model $0.82 = 2.1x. Peer PRTH: 9.8x. MQ: 24x. Street $0.08 = 21.3x. Massive discount on ANY scenario that incorporates ESA catalysts.
A82: Price target (15x FY2027 EPS) | B82: $6.30 (thesis anchor) | C82: $7.09 (model) | D82: $3.87 (model) | E82: $2.18 (model) | F82: Thesis applies 15x conservative fintech multiple to $0.42 EPS = $6.30, consistent with Ladenburg $6.25 and HC Wainwright $4.00 analyst targets. Use $6.30 as institutional communication anchor (thesis-calibrated).
A83: Risk/reward ($6.30 bull / $0.75 bear) | B83: 3.7:1 (model) / 3.8:1 (thesis) | C83: 4.1:1 | D83: 2.3:1 | E83: — | F83: Bear floor: 15x x $0.05 EPS = $0.75. The asymmetry is real because the downside is bounded by the existing core business generating ~$2M/yr baseline NI with $6.4M net cash cushion.
A84: EV/Adj. EBITDA FY2027E | B84: 0.6x (model) | C84: 1.2x | D84: 2.4x | E84: 2.7x | F84: Thesis CCA grid: PRTH 7.4x, MQ 14.2x. Usio at even 4x EBITDA (base case) is massively discounted. Catalyst execution changes this to 0.6x on our bull model — structurally undervalued.
A86: 7. AUGUST 15, 2026 EARNINGS CALL — 8 KEY FLAGS TO WATCH
A87: Flag / KPI | B87: Bull Signal | C87: Bear Warning | D87: Bull Target | E87: Bear Red Flag | F87: Analysis
A88: TX ESA July 1 cash (MOST CRITICAL) | B88: CRITICAL BULL TRIGGER | C88: CRITICAL BEAR WARNING | D88: $200-250M+ confirmed in ecosystem | E88: Delay language / legislative hold / Q3 push | F88: By Aug 15, mgmt has 45 days of live Q3 data. $250M confirmation triggers algorithmic quant scanners — thesis models stock gap to $2.85-$3.15 Day 1-3 on 10x+ volume surge. Any delay language = bear case.
A89: Full-year guidance revision | B89: MAJOR CATALYST | C89: MAJOR DISAPPOINTMENT | D89: EPS guidance initiated OR revenue guidance raised above 12% | E89: Guidance maintained flat or reduced | F89: Currently no EPS guidance given (only 10-12% revenue). If Tom Gomez initiates any positive EPS number: 566% beat above -$0.03 consensus per thesis variance model. Even $0.07 FY2026 = massive paradigm shift.
A90: ACH & RTP velocity | B90: BULL CONFIRMER | C90: BEAR SIGNAL | D90: ACH Q2 revenue >$6.0M (+15%+ YoY from $5.19M Q2 2025) | E90: ACH deceleration; RTP "leveling off" | F90: April = best single ACH month ever. RTP at 200K txns/month exiting Q1. If Q2 ACH re-accelerates despite seasonal softness, the RTP 100x trajectory is monetizing into revenue.
A91: Card/PayFac trajectory | B91: BULL | C91: BEAR | D91: Q2 card >$8.0M (PayFac sustaining 20%+ growth) | E91: Q2 card <$7.5M (Q1 was seasonal peak) | F91: PayFac at 78% of card and >20% growth. New building supply + sporting goods retailers full quarter. Q2 2025 was $7.0M — if Q2 2026 shows $8.0M+ it confirms the PayFac engine has permanently overcome legacy attrition.
A92: SG&A overhead — THE KEY LEVER | B92: BULL CONFIRMER | C92: BEAR RISK | D92: SG&A $4.3-4.5M (flat to down from Q1's $4.4M) | E92: SG&A >$4.7M (headcount additions for programs) | F92: The thesis ENTIRE operating leverage story depends on this number. "91.2% of every incremental GP dollar flows past the operating line" ONLY if SG&A stays flat. Every $100K above $4.5M = ~$70K after-tax EPS erosion.
A93: Output Solutions printer confirmation | B93: BULL | C93: BEAR | D93: Printer confirmed online late June/July; electronic docs >35% YoY | E93: Printer delayed to Q3; Q2 GM <21% | F93: CEO confirmed printer arriving June. Watch for explicit confirmation it is live. Electronic presentment growth rate must hold >35% to validate the margin step-up thesis for H2 2026.
A94: Indiana/Ohio pipeline mention | B94: UPSIDE OPTION | C94: NEUTRAL | D94: Any mention of second-state ESA RFP or government payment modernization pipeline | E94: Silence (neutral) | F94: Indiana went universal July 2026. If mgmt mentions any state government payment RFP on Aug 15 call, it validates multi-state expansion. Indiana alone = $1,700K/yr incremental revenue if won. Worth $0.03-0.04 to 2027 EPS.
A95: PostCredit onboarding velocity | B95: BULL OPTION | C95: BEAR RISK | D95: >50% of new clients accepting auto-provisioned PostCredit account | E95: Integration friction or merchant resistance language | F95: First quantitative PostCredit metrics expected. 50%+ auto-provision rate = cross-sell flywheel confirmed. Every PostCredit client = elevated LTV + lower churn permanently. No metrics = still speculative but manageable.
A97: 8. THE INFORMATION ASYMMETRY — WHY THE STREET IS MISSING THIS STORY
A98: Street consensus FY2026 EPS | B98: -$0.03 to -$0.04 | C98: -$0.03 | D98: -$0.03 to -$0.04 | E98: NM | F98: Set BEFORE Q1 2026 print. Q1 actual: +$0.00 EPS (profitable). Street has not updated for TX ESA program (July 1 live), 1.65% stepped take-rate, or flat overhead cap. "Treating Usio like a standard legacy transaction processor" per thesis.
A99: Street consensus FY2027 EPS | B99: $0.08 vs $0.42 thesis | C99: $0.08 vs $0.21 | D99: $0.08 vs $0.26 | E99: $0.08 vs $0.15 | F99: Three miss-sources per thesis: (1) No ESA float interest modeled; (2) Generic 1.25% take-rate vs stepped 1.65%; (3) Variable cost growth modeled vs the fixed $4.4M/qtr overhead cap. "91.2% of every incremental GP dollar flows past the operating line" — the flat overhead multiplier is the key analytical miss.
A100: Management camouflage strategy | B100: Conservative guidance + catalysts in commentary | C100: Same | D100: Guidance anchor | E100: Worst case | F100: Thesis: "Paul Manley and the executive team provided the critical building blocks needed to forecast growth. However, by packaging these metrics alongside a flat full-year guidance forecast, they avoided premature market hype — creating a classic information asymmetry." What mgmt said: RTP 100x, $1B voucher, April best ACH month, PayFac 78%. What Street heard: "guidance unchanged 10-12%."
A101: August 15 inflection | B101: $250M float + positive EPS guidance → stock gaps $1.71→$2.85+ | C101: $0.07 EPS guided → 10x+ volume Day 1 | D101: No change | E101: Delay → reversal | F101: Thesis micro-cap liquidity model: Day 1-3: algorithmic quant scanners trigger on guidance revision from -$0.03→+$0.07. 10x+ volume (120K→1.5M+ shares/day). Stock gaps past $3.00. Day 4-15: sell-side forced model revisions, "Upgrading to Buy." Day 16-30: long-only small-cap funds pass liquidity filter at 350K+ ADV, institutional floor $3.50-$4.20 established.

Sheet Ratios & Analysis
A1: Usio, Inc. — CFA-Style Ratio Analysis (Quarterly)
A2: Profitability, liquidity, leverage, efficiency, and cash flow metrics
A4: Fiscal Period | B4: 2025Q1A | C4: 2025Q2A | D4: 2025Q3A | E4: 2025Q4A | F4: FY2025A | G4: 2026Q1A | H4: 2026Q2E | I4: 2026Q3E | J4: 2026Q4E | K4: FY2026E | L4: 2027Q1E | M4: 2027Q2E | N4: 2027Q3E | O4: 2027Q4E | P4: FY2027E | Q4: 2028Q1E | R4: 2028Q2E | S4: 2028Q3E | T4: 2028Q4E | U4: FY2028E
A6: Profitability (quarterly)
A7: Gross margin % | B7: ='Income Statement'!B9 -> 0.21850752 | C7: ='Income Statement'!C9 -> 0.25750571 | D7: ='Income Statement'!D9 -> 0.22993118 | E7: ='Income Statement'!E9 -> 0.22032374 | F7: ='Income Statement'!F9 -> 0.23093038 | G7: ='Income Statement'!G9 -> 0.20171712 | H7: ='Income Statement'!H9 -> 0.225 | I7: ='Income Statement'!I9 -> 0.228 | ... U7: ='Income Statement'!U9 -> 0.225
A8: Operating margin % | B8: ='Income Statement'!B19 -> -0.010885704 | C8: ='Income Statement'!C19 -> 0.022411063 | D8: ='Income Statement'!D19 -> -0.0030494799 | E8: ='Income Statement'!E19 -> 0.052880261 | F8: ='Income Statement'!F19 -> 0.015449411 | G8: ='Income Statement'!G19 -> 0.0088633466 | H8: ='Income Statement'!H19 -> 0.036 | I8: ='Income Statement'!I19 -> 0.039 | ... U8: ='Income Statement'!U19 -> 0.036
A9: Net margin % | B9: ='Income Statement'!B25 -> -0.010676063 | C9: ='Income Statement'!C25 -> -0.018368327 | D9: ='Income Statement'!D25 -> -0.018885444 | E9: ='Income Statement'!E25 -> -0.067446043 | F9: ='Income Statement'!F25 -> -0.029296277 | G9: ='Income Statement'!G25 -> 0.0075068594 | H9: ='Income Statement'!H25 -> 0.029537271 | I9: ='Income Statement'!I25 -> 0.031387576 | ... U9: ='Income Statement'!U25 -> 0.028669758
A10: Adj. EBITDA margin % | B10: ='Income Statement'!B33 -> 0.030271547 | C10: ='Income Statement'!C33 -> 0.067441595 | D10: ='Income Statement'!D33 -> 0.036252452 | E10: ='Income Statement'!E33 -> 0.082967851 | F10: ='Income Statement'!F33 -> 0.054168788 | G10: ='Income Statement'!G33 -> 0.030658441 | H10: ='Income Statement'!H33 -> 0.06 | I10: ='Income Statement'!I33 -> 0.063 | ... U10: ='Income Statement'!U33 -> 0.06
A11: Return on Assets (ROA, annualized) | B11: ='Income Statement'!B24*4/'Balance Sheet'!B25 -> -0.0087095793 | C11: ='Income Statement'!C24*4/'Balance Sheet'!C25 -> -0.014697006 | D11: ='Income Statement'!D24*4/'Balance Sheet'!D25 -> -0.015296415 | E11: ='Income Statement'!E24*4/'Balance Sheet'!E25 -> -0.044480617 | F11: ='Income Statement'!F24/'Balance Sheet'!F25 -> -0.0185456 | G11: ='Income Statement'!G24*4/'Balance Sheet'!G25 -> 0.006362066 | H11: ='Income Statement'!H24*4/'Balance Sheet'!H25 -> 0.023437677 | I11: ='Income Statement'!I24*4/'Balance Sheet'!I25 -> 0.025045519 | J11: ='Income Statement'!J24*4/'Balance Sheet'!J25 -> 0.026005186 | K11: ='Income Statement'!K24/'Balance Sheet'!K25 -> 0.019720142 | L11: ='Income Statement'!L24*4/'Balance Sheet'!L25 -> 0.023307387 | M11: ='Income Statement'!M24*4/'Balance Sheet'!M25 -> 0.022912928 | N11: ='Income Statement'!N24*4/'Balance Sheet'!N25 -> 0.022876892 | O11: ='Income Statement'!O24*4/'Balance Sheet'!O25 -> 0.022752334 | P11: ='Income Statement'!P24/'Balance Sheet'!P25 -> 0.022710871 | Q11: ='Income Statement'!Q24*4/'Balance Sheet'!Q25 -> 0.022886535 | R11: ='Income Statement'!R24*4/'Balance Sheet'!R25 -> 0.022445637 | S11: ='Income Statement'!S24*4/'Balance Sheet'!S25 -> 0.022430229 | T11: ='Income Statement'!T24*4/'Balance Sheet'!T25 -> 0.022310489 | U11: ='Income Statement'!U24/'Balance Sheet'!U25 -> 0.022269437
A12: Return on Equity (ROE, annualized) | B12: ='Income Statement'!B24*4/'Balance Sheet'!B48 -> -0.046577012 | C12: ='Income Statement'!C24*4/'Balance Sheet'!C48 -> -0.074024337 | D12: ='Income Statement'!D24*4/'Balance Sheet'!D48 -> -0.082421532 | E12: ='Income Statement'!E24*4/'Balance Sheet'!E48 -> -0.33496343 | F12: ='Income Statement'!F24/'Balance Sheet'!F48 -> -0.13965854 | G12: ='Income Statement'!G24*4/'Balance Sheet'!G48 -> 0.042142505 | H12: ='Income Statement'!H24*4/'Balance Sheet'!H48 -> 0.13787385 | I12: ='Income Statement'!I24*4/'Balance Sheet'!I48 -> 0.14838563 | J12: ='Income Statement'!J24*4/'Balance Sheet'!J48 -> 0.1495071 | K12: ='Income Statement'!K24/'Balance Sheet'!K48 -> 0.11337359 | L12: ='Income Statement'!L24*4/'Balance Sheet'!L48 -> 0.14471698 | M12: ='Income Statement'!M24*4/'Balance Sheet'!M48 -> 0.12305822 | N12: ='Income Statement'!N24*4/'Balance Sheet'!N48 -> 0.12446091 | O12: ='Income Statement'!O24*4/'Balance Sheet'!O48 -> 0.12096674 | P12: ='Income Statement'!P24/'Balance Sheet'!P48 -> 0.12074629 | Q12: ='Income Statement'!Q24*4/'Balance Sheet'!Q48 -> 0.13176879 | R12: ='Income Statement'!R24*4/'Balance Sheet'!R48 -> 0.11225018 | S12: ='Income Statement'!S24*4/'Balance Sheet'!S48 -> 0.1139248 | T12: ='Income Statement'!T24*4/'Balance Sheet'!T48 -> 0.11104586 | U12: ='Income Statement'!U24/'Balance Sheet'!U48 -> 0.11084154
A13: Liquidity
A14: Current ratio | B14: ='Balance Sheet'!B16/'Balance Sheet'!B37 -> 1.0944386 | C14: ='Balance Sheet'!C16/'Balance Sheet'!C37 -> 1.1004385 | D14: ='Balance Sheet'!D16/'Balance Sheet'!D37 -> 1.0963503 | E14: ='Balance Sheet'!E16/'Balance Sheet'!E37 -> 1.0823871 | F14: ='Balance Sheet'!F16/'Balance Sheet'!F37 -> 1.0823871 | G14: ='Balance Sheet'!G16/'Balance Sheet'!G37 -> 1.0918102 | H14: ='Balance Sheet'!H16/'Balance Sheet'!H37 -> 1.1110289 | I14: ='Balance Sheet'!I16/'Balance Sheet'!I37 -> 1.1150069 | ... U14: ='Balance Sheet'!U16/'Balance Sheet'!U37 -> 1.1815709
A15: Quick ratio (cash + AR / current liab.) | B15: =('Balance Sheet'!B8+'Balance Sheet'!B9)/'Balance Sheet'!B37 -> 0.13708383 | C15: =('Balance Sheet'!C8+'Balance Sheet'!C9)/'Balance Sheet'!C37 -> 0.14498192 | D15: =('Balance Sheet'!D8+'Balance Sheet'!D9)/'Balance Sheet'!D37 -> 0.13978457 | E15: =('Balance Sheet'!E8+'Balance Sheet'!E9)/'Balance Sheet'!E37 -> 0.11146254 | F15: =('Balance Sheet'!F8+'Balance Sheet'!F9)/'Balance Sheet'!F37 -> 0.11146254 | G15: =('Balance Sheet'!G8+'Balance Sheet'!G9)/'Balance Sheet'!G37 -> 0.13379095 | H15: =('Balance Sheet'!H8+'Balance Sheet'!H9)/'Balance Sheet'!H37 -> 0.15185542 | I15: =('Balance Sheet'!I8+'Balance Sheet'!I9)/'Balance Sheet'!I37 -> 0.15651541 | ... U15: =('Balance Sheet'!U8+'Balance Sheet'!U9)/'Balance Sheet'!U37 -> 0.22463439
A16: Cash ratio | B16: ='Balance Sheet'!B8/'Balance Sheet'!B37 -> 0.084931269 | C16: ='Balance Sheet'!C8/'Balance Sheet'!C37 -> 0.0930478 | D16: ='Balance Sheet'!D8/'Balance Sheet'!D37 -> 0.087718969 | E16: ='Balance Sheet'!E8/'Balance Sheet'!E37 -> 0.065201184 | F16: ='Balance Sheet'!F8/'Balance Sheet'!F37 -> 0.065201184 | G16: ='Balance Sheet'!G8/'Balance Sheet'!G37 -> 0.078649698 | H16: ='Balance Sheet'!H8/'Balance Sheet'!H37 -> 0.099890209 | I16: ='Balance Sheet'!I8/'Balance Sheet'!I37 -> 0.10450646 | ... U16: ='Balance Sheet'!U8/'Balance Sheet'!U37 -> 0.17250702
A17: Working capital ($000) | B17: ='Balance Sheet'!B16-'Balance Sheet'!B37 -> 8321.2291 | C17: ='Balance Sheet'!C16-'Balance Sheet'!C37 -> 8060.1239 | D17: ='Balance Sheet'!D16-'Balance Sheet'!D37 -> 8183.656 | E17: ='Balance Sheet'!E16-'Balance Sheet'!E37 -> 9393.537 | F17: ='Balance Sheet'!F16-'Balance Sheet'!F37 -> 9393.537 | G17: ='Balance Sheet'!G16-'Balance Sheet'!G37 -> 9022.058 | H17: ='Balance Sheet'!H16-'Balance Sheet'!H37 -> 9863.6524 | I17: ='Balance Sheet'!I16-'Balance Sheet'!I37 -> 10832.051 | ... U17: ='Balance Sheet'!U16-'Balance Sheet'!U37 -> 20142.895
A18: Leverage / Solvency
A19: Total liabilities / Total assets | B19: ='Balance Sheet'!B43/'Balance Sheet'!B25 -> 0.84394801 | C19: ='Balance Sheet'!C43/'Balance Sheet'!C25 -> 0.8338596 | D19: ='Balance Sheet'!D43/'Balance Sheet'!D25 -> 0.84031956 | E19: ='Balance Sheet'!E43/'Balance Sheet'!E25 -> 0.86720754 | F19: ='Balance Sheet'!F43/'Balance Sheet'!F25 -> 0.86720754 | G19: ='Balance Sheet'!G43/'Balance Sheet'!G25 -> 0.84903446 | H19: ='Balance Sheet'!H43/'Balance Sheet'!H25 -> 0.83000636 | I19: ='Balance Sheet'!I43/'Balance Sheet'!I25 -> 0.83121331 | ... U19: ='Balance Sheet'!U43/'Balance Sheet'!U25 -> 0.79908762
A20: Equipment loans / Total equity | B20: =('Balance Sheet'!B32+'Balance Sheet'!B40)/'Balance Sheet'!B48 -> 0.067596235 | C20: =('Balance Sheet'!C32+'Balance Sheet'!C40)/'Balance Sheet'!C48 -> 0.068847176 | D20: =('Balance Sheet'!D32+'Balance Sheet'!D40)/'Balance Sheet'!D48 -> 0.070265799 | E20: =('Balance Sheet'!E32+'Balance Sheet'!E40)/'Balance Sheet'!E48 -> 0.076149917 | F20: =('Balance Sheet'!F32+'Balance Sheet'!F40)/'Balance Sheet'!F48 -> 0.076149917 | G20: =('Balance Sheet'!G32+'Balance Sheet'!G40)/'Balance Sheet'!G48 -> 0.07305299 | H20: =('Balance Sheet'!H32+'Balance Sheet'!H40)/'Balance Sheet'!H48 -> 0.067351593 | I20: =('Balance Sheet'!I32+'Balance Sheet'!I40)/'Balance Sheet'!I48 -> 0.061922365 | ... U20: =('Balance Sheet'!U32+'Balance Sheet'!U40)/'Balance Sheet'!U48 -> 0.031456334
A21: Efficiency
A22: Days Sales Outstanding (AR) | B22: ='Balance Sheet'!B9/'Income Statement'!B6*91 -> 19 | C22: ='Balance Sheet'!C9/'Income Statement'!C6*91 -> 19 | D22: ='Balance Sheet'!D9/'Income Statement'!D6*91 -> 19 | E22: ='Balance Sheet'!E9/'Income Statement'!E6*91 -> 21.582164 | F22: ='Balance Sheet'!F9/'Income Statement'!F6*91 -> 5.6210941 | G22: ='Balance Sheet'!G9/'Income Statement'!G6*91 -> 19.363141 | H22: ='Balance Sheet'!H9/'Income Statement'!H6*91 -> 19 | I22: ='Balance Sheet'!I9/'Income Statement'!I6*91 -> 19 | ... U22: ='Balance Sheet'!U9/'Income Statement'!U6*91 -> 4.7599618
A23: Days Payable Outstanding (AP) | B23: ='Balance Sheet'!B29/'Income Statement'!B10*91 -> 7 | C23: ='Balance Sheet'!C29/'Income Statement'!C10*91 -> 7 | D23: ='Balance Sheet'!D29/'Income Statement'!D10*91 -> 7 | E23: ='Balance Sheet'!E29/'Income Statement'!E10*91 -> 4.6213201 | F23: ='Balance Sheet'!F29/'Income Statement'!F10*91 -> 1.2202268 | G23: ='Balance Sheet'!G29/'Income Statement'!G10*91 -> 5.707667 | H23: ='Balance Sheet'!H29/'Income Statement'!H10*91 -> 7 | I23: ='Balance Sheet'!I29/'Income Statement'!I10*91 -> 7 | ... U23: ='Balance Sheet'!U29/'Income Statement'!U10*91 -> 1.7536701
A24: Cash Flow
A25: CFO ($000) | B25: ='Cash Flow Statement'!B17 -> 670.862 | C25: ='Cash Flow Statement'!C17 -> 776.822 | D25: ='Cash Flow Statement'!D17 -> 292.40859 | E25: ='Cash Flow Statement'!E17 -> -2057.2202 | F25: ='Cash Flow Statement'!F17 -> -317.12762 | G25: ='Cash Flow Statement'!G17 -> 1314.374 | H25: ='Cash Flow Statement'!H17 -> 1774.9216 | I25: ='Cash Flow Statement'!I17 -> 1623.1091 | ... U25: ='Cash Flow Statement'!U17 -> 7201.7594
A26: Free cash flow ($000, CFO + Capex) | B26: ='Cash Flow Statement'!B17+'Cash Flow Statement'!B20 -> 357.608 | C26: ='Cash Flow Statement'!C17+'Cash Flow Statement'!C20 -> 463.568 | D26: ='Cash Flow Statement'!D17+'Cash Flow Statement'!D20 -> -20.845407 | E26: ='Cash Flow Statement'!E17+'Cash Flow Statement'!E20 -> -2370.4742 | F26: ='Cash Flow Statement'!F17+'Cash Flow Statement'!F20 -> -1570.1436 | G26: ='Cash Flow Statement'!G17+'Cash Flow Statement'!G20 -> 700.77 | H26: ='Cash Flow Statement'!H17+'Cash Flow Statement'!H20 -> 1332.708 | I26: ='Cash Flow Statement'!I17+'Cash Flow Statement'!I20 -> 1153.8824 | ... U26: ='Cash Flow Statement'!U17+'Cash Flow Statement'!U20 -> 4990.6543
A27: FCF margin % | B27: =('Cash Flow Statement'!B17+'Cash Flow Statement'!B20)/'Income Statement'!B6 -> 0.016248225 | C27: =('Cash Flow Statement'!C17+'Cash Flow Statement'!C20)/'Income Statement'!C6 -> 0.023223698 | D27: =('Cash Flow Statement'!D17+'Cash Flow Statement'!D20)/'Income Statement'!D6 -> -0.00098418691 | E27: =('Cash Flow Statement'!E17+'Cash Flow Statement'!E20)/'Income Statement'!E6 -> -0.10658607 | F27: =('Cash Flow Statement'!F17+'Cash Flow Statement'!F20)/'Income Statement'!F6 -> -0.018387829 | G27: =('Cash Flow Statement'!G17+'Cash Flow Statement'!G20)/'Income Statement'!G6 -> 0.027518109 | H27: =('Cash Flow Statement'!H17+'Cash Flow Statement'!H20)/'Income Statement'!H6 -> 0.060274409 | I27: =('Cash Flow Statement'!I17+'Cash Flow Statement'!I20)/'Income Statement'!I6 -> 0.049182296 | ... U27: =('Cash Flow Statement'!U17+'Cash Flow Statement'!U20)/'Income Statement'!U6 -> 0.045141718
A28: Per-Share
A29: Diluted EPS | B29: ='Income Statement'!B28 -> -0.0088281661 | C29: ='Income Statement'!C28 -> -0.013655493 | D29: ='Income Statement'!D28 -> -0.014814815 | E29: ='Income Statement'!E28 -> -0.054945055 | F29: ='Income Statement'!F28 -> -0.092853821 | G29: ='Income Statement'!G28 -> 0.0068894243 | H29: ='Income Statement'!H28 -> 0.023492413 | I29: ='Income Statement'!I28 -> 0.026489011 | ... U29: ='Income Statement'!U28 -> 0.11401412
A30: Note: market price, P/E, EV/EBITDA omitted -- would require live market data. As of the 3/31/2026 Seeking Alpha pull, shares traded around $1.14.
